<object stamp="26abc375-bcb2-4d6b-86e4-372e1911d005_1604077932879" type="DataSource" version="9.0">
    <property name="objectId" value="84940025-1c39-4ea9-aec0-5eb6bc483e96" valueType="string"/>
    <property name="branchId" value="63fa0e79-2f54-410a-b939-634c9e9fc492" valueType="string"/>
    <property name="name" value="VISIONR_CEXOWBN" valueType="string"/>
    <property name="description" value="DataSource VISIONR_CEXOWBN : Beneficiarios de garantías, para entes territoriales, nación y entidades financieras" valueType="string"/>
    <property name="hosting" value="INTERNAL" valueType="string"/>
    <property name="dbSource" valueType="url">DBSource["SHDATASP"{2cd42932-215e-44fa-a8c0-33ab9aaf6d3e}]</property>
    <property name="defaultVisibilityInModel" value="true" valueType="boolean"/>
    <property name="dataStructure" value="FLAT" valueType="string"/>
    <property name="layout" valueType="table">
        <object type="DataSource:field" version="3.0">
            <property name="id" value="56bb12ba-0cb7-48d2-b13e-40cc6072e690" valueType="string"/>
            <property name="name" value="asof_date" valueType="string"/>
            <property name="description" value="" valueType="string"/>
            <property name="title" value="" valueType="string"/>
            <property name="type" value="DATE" valueType="string"/>
            <property name="allowNulls" value="true" valueType="boolean"/>
            <property name="allowDefault" value="false" valueType="boolean"/>
            <property name="syntheticContent" valueType="table"/>
            <property name="lookupSource" valueType="url"/>
            <property name="parentFields" valueType="table"/>
            <property name="aggregatedFunction" value="" valueType="string"/>
            <property name="isCountFieldFor" valueType="url"/>
            <property name="displayFormat" value="" valueType="string"/>
            <property name="showSubtotal" value="false" valueType="boolean"/>
            <property name="isHidden" value="false" valueType="boolean"/>
            <property name="defaultInstanceKeyValueFormula" valueType="object">
                <object type="ASLExpression" version="1.0">
                    <property name="expression" valueType="table"/>
                </object>
            </property>
        </object>
        <object type="DataSource:field" version="3.0">
            <property name="id" value="c2029dac-42ca-419d-8cc4-639c657ceb0d" valueType="string"/>
            <property name="name" value="version" valueType="string"/>
            <property name="description" value="" valueType="string"/>
            <property name="title" value="" valueType="string"/>
            <property name="type" value="INTEGER" valueType="string"/>
            <property name="allowNulls" value="true" valueType="boolean"/>
            <property name="allowDefault" value="false" valueType="boolean"/>
            <property name="syntheticContent" valueType="table"/>
            <property name="lookupSource" valueType="url"/>
            <property name="parentFields" valueType="table"/>
            <property name="aggregatedFunction" value="" valueType="string"/>
            <property name="isCountFieldFor" valueType="url"/>
            <property name="displayFormat" value="" valueType="string"/>
            <property name="showSubtotal" value="false" valueType="boolean"/>
            <property name="isHidden" value="false" valueType="boolean"/>
            <property name="defaultInstanceKeyValueFormula" valueType="object">
                <object type="ASLExpression" version="1.0">
                    <property name="expression" valueType="table"/>
                </object>
            </property>
        </object>
        <object type="DataSource:field" version="3.0">
            <property name="id" value="7a55b0a9-8f3f-4d16-be9a-cf2d2f3a206b" valueType="string"/>
            <property name="name" value="filing_version" valueType="string"/>
            <property name="description" value="" valueType="string"/>
            <property name="title" value="" valueType="string"/>
            <property name="type" value="INTEGER" valueType="string"/>
            <property name="allowNulls" value="true" valueType="boolean"/>
            <property name="allowDefault" value="false" valueType="boolean"/>
            <property name="syntheticContent" valueType="table"/>
            <property name="lookupSource" valueType="url"/>
            <property name="parentFields" valueType="table"/>
            <property name="aggregatedFunction" value="" valueType="string"/>
            <property name="isCountFieldFor" valueType="url"/>
            <property name="displayFormat" value="" valueType="string"/>
            <property name="showSubtotal" value="false" valueType="boolean"/>
            <property name="isHidden" value="false" valueType="boolean"/>
            <property name="defaultInstanceKeyValueFormula" valueType="object">
                <object type="ASLExpression" version="1.0">
                    <property name="expression" valueType="table"/>
                </object>
            </property>
        </object>
        <object type="DataSource:field" version="3.0">
            <property name="id" value="445fb14b-a764-4930-b883-bd0fef571ddd" valueType="string"/>
            <property name="name" value="axiom_index" valueType="string"/>
            <property name="description" value="" valueType="string"/>
            <property name="title" value="" valueType="string"/>
            <property name="type" value="INTEGER" valueType="string"/>
            <property name="allowNulls" value="false" valueType="boolean"/>
            <property name="allowDefault" value="false" valueType="boolean"/>
            <property name="syntheticContent" valueType="table"/>
            <property name="lookupSource" valueType="url"/>
            <property name="parentFields" valueType="table"/>
            <property name="aggregatedFunction" value="" valueType="string"/>
            <property name="isCountFieldFor" valueType="url"/>
            <property name="displayFormat" value="" valueType="string"/>
            <property name="showSubtotal" value="false" valueType="boolean"/>
            <property name="isHidden" value="false" valueType="boolean"/>
            <property name="defaultInstanceKeyValueFormula" valueType="object">
                <object type="ASLExpression" version="1.0">
                    <property name="expression" valueType="table"/>
                </object>
            </property>
        </object>
        <object type="DataSource:field" version="3.0">
            <property name="id" value="b22d9165-8d56-43ff-9ec5-1fcbfc07260e" valueType="string"/>
            <property name="name" value="XONOCO" valueType="string"/>
            <property name="description" value="XONOCO_Número de Garantía" valueType="string"/>
            <property name="title" value="" valueType="string"/>
            <property name="type" value="VARCHAR" valueType="string"/>
            <property name="size" value="30" valueType="integer"/>
            <property name="allowNulls" value="false" valueType="boolean"/>
            <property name="allowDefault" value="true" valueType="boolean"/>
            <property name="isAutoUniqueId" value="false" valueType="boolean"/>
            <property name="defaultValue" value="''" valueType="string"/>
            <property name="syntheticContent" valueType="table"/>
            <property name="lookupSource" valueType="url"/>
            <property name="parentFields" valueType="table"/>
            <property name="aggregatedFunction" value="" valueType="string"/>
            <property name="isCountFieldFor" valueType="url"/>
            <property name="displayFormat" value="" valueType="string"/>
            <property name="showSubtotal" value="false" valueType="boolean"/>
            <property name="isHidden" value="false" valueType="boolean"/>
            <property name="defaultInstanceKeyValueFormula" valueType="object">
                <object type="ASLExpression" version="1.0">
                    <property name="expression" valueType="table"/>
                </object>
            </property>
        </object>
        <object type="DataSource:field" version="3.0">
            <property name="id" value="6cdc2477-692f-44c0-a0fe-a2ecc0b8e53a" valueType="string"/>
            <property name="name" value="XOCDOB" valueType="string"/>
            <property name="description" value="XOCDOB_Propietario" valueType="string"/>
            <property name="title" value="" valueType="string"/>
            <property name="type" value="VARCHAR" valueType="string"/>
            <property name="size" value="1" valueType="integer"/>
            <property name="allowNulls" value="false" valueType="boolean"/>
            <property name="allowDefault" value="true" valueType="boolean"/>
            <property name="isAutoUniqueId" value="false" valueType="boolean"/>
            <property name="defaultValue" value="''" valueType="string"/>
            <property name="syntheticContent" valueType="table"/>
            <property name="lookupSource" valueType="url"/>
            <property name="parentFields" valueType="table"/>
            <property name="aggregatedFunction" value="" valueType="string"/>
            <property name="isCountFieldFor" valueType="url"/>
            <property name="displayFormat" value="" valueType="string"/>
            <property name="showSubtotal" value="false" valueType="boolean"/>
            <property name="isHidden" value="false" valueType="boolean"/>
            <property name="defaultInstanceKeyValueFormula" valueType="object">
                <object type="ASLExpression" version="1.0">
                    <property name="expression" valueType="table"/>
                </object>
            </property>
        </object>
        <object type="DataSource:field" version="3.0">
            <property name="id" value="1b416f18-3ec6-426c-89ae-49a29bea5095" valueType="string"/>
            <property name="name" value="XONOTX" valueType="string"/>
            <property name="description" value="XONOTX" valueType="string"/>
            <property name="title" value="" valueType="string"/>
            <property name="type" value="VARCHAR" valueType="string"/>
            <property name="size" value="15" valueType="integer"/>
            <property name="allowNulls" value="false" valueType="boolean"/>
            <property name="allowDefault" value="true" valueType="boolean"/>
            <property name="isAutoUniqueId" value="false" valueType="boolean"/>
            <property name="defaultValue" value="''" valueType="string"/>
            <property name="syntheticContent" valueType="table"/>
            <property name="lookupSource" valueType="url"/>
            <property name="parentFields" valueType="table"/>
            <property name="aggregatedFunction" value="" valueType="string"/>
            <property name="isCountFieldFor" valueType="url"/>
            <property name="displayFormat" value="" valueType="string"/>
            <property name="showSubtotal" value="false" valueType="boolean"/>
            <property name="isHidden" value="false" valueType="boolean"/>
            <property name="defaultInstanceKeyValueFormula" valueType="object">
                <object type="ASLExpression" version="1.0">
                    <property name="expression" valueType="table"/>
                </object>
            </property>
        </object>
        <object type="DataSource:field" version="3.0">
            <property name="id" value="986d4e96-9ae4-402c-a0bb-ba2dc026c1a8" valueType="string"/>
            <property name="name" value="XONAMK" valueType="string"/>
            <property name="description" value="XONAMK" valueType="string"/>
            <property name="title" value="" valueType="string"/>
            <property name="type" value="VARCHAR" valueType="string"/>
            <property name="size" value="50" valueType="integer"/>
            <property name="allowNulls" value="false" valueType="boolean"/>
            <property name="allowDefault" value="true" valueType="boolean"/>
            <property name="isAutoUniqueId" value="false" valueType="boolean"/>
            <property name="defaultValue" value="''" valueType="string"/>
            <property name="syntheticContent" valueType="table"/>
            <property name="lookupSource" valueType="url"/>
            <property name="parentFields" valueType="table"/>
            <property name="aggregatedFunction" value="" valueType="string"/>
            <property name="isCountFieldFor" valueType="url"/>
            <property name="displayFormat" value="" valueType="string"/>
            <property name="showSubtotal" value="false" valueType="boolean"/>
            <property name="isHidden" value="false" valueType="boolean"/>
            <property name="defaultInstanceKeyValueFormula" valueType="object">
                <object type="ASLExpression" version="1.0">
                    <property name="expression" valueType="table"/>
                </object>
            </property>
        </object>
        <object type="DataSource:field" version="3.0">
            <property name="id" value="5595194f-9b77-4686-824e-471a724c3b5f" valueType="string"/>
            <property name="name" value="XOPP01" valueType="string"/>
            <property name="description" value="XOPP01" valueType="string"/>
            <property name="title" value="" valueType="string"/>
            <property name="type" value="FLOAT" valueType="string"/>
            <property name="allowNulls" value="false" valueType="boolean"/>
            <property name="allowDefault" value="true" valueType="boolean"/>
            <property name="defaultValue" value="0" valueType="string"/>
            <property name="syntheticContent" valueType="table"/>
            <property name="lookupSource" valueType="url"/>
            <property name="parentFields" valueType="table"/>
            <property name="aggregatedFunction" value="" valueType="string"/>
            <property name="isCountFieldFor" valueType="url"/>
            <property name="displayFormat" value="" valueType="string"/>
            <property name="showSubtotal" value="false" valueType="boolean"/>
            <property name="isHidden" value="false" valueType="boolean"/>
            <property name="defaultInstanceKeyValueFormula" valueType="object">
                <object type="ASLExpression" version="1.0">
                    <property name="expression" valueType="table"/>
                </object>
            </property>
        </object>
        <object type="DataSource:field" version="3.0">
            <property name="id" value="3ed75ab1-c71d-4280-a4a6-caba2940e4f5" valueType="string"/>
            <property name="name" value="XAMTNU" valueType="string"/>
            <property name="description" value="XAMTNU" valueType="string"/>
            <property name="title" value="" valueType="string"/>
            <property name="type" value="FLOAT" valueType="string"/>
            <property name="allowNulls" value="false" valueType="boolean"/>
            <property name="allowDefault" value="true" valueType="boolean"/>
            <property name="defaultValue" value="0" valueType="string"/>
            <property name="syntheticContent" valueType="table"/>
            <property name="lookupSource" valueType="url"/>
            <property name="parentFields" valueType="table"/>
            <property name="aggregatedFunction" value="" valueType="string"/>
            <property name="isCountFieldFor" valueType="url"/>
            <property name="displayFormat" value="" valueType="string"/>
            <property name="showSubtotal" value="false" valueType="boolean"/>
            <property name="isHidden" value="false" valueType="boolean"/>
            <property name="defaultInstanceKeyValueFormula" valueType="object">
                <object type="ASLExpression" version="1.0">
                    <property name="expression" valueType="table"/>
                </object>
            </property>
        </object>
        <object type="DataSource:field" version="3.0">
            <property name="id" value="841be33d-458a-4c65-a1a6-3da9f56ce641" valueType="string"/>
            <property name="name" value="XAMTUS" valueType="string"/>
            <property name="description" value="XAMTUS" valueType="string"/>
            <property name="title" value="" valueType="string"/>
            <property name="type" value="FLOAT" valueType="string"/>
            <property name="allowNulls" value="false" valueType="boolean"/>
            <property name="allowDefault" value="true" valueType="boolean"/>
            <property name="defaultValue" value="0" valueType="string"/>
            <property name="syntheticContent" valueType="table"/>
            <property name="lookupSource" valueType="url"/>
            <property name="parentFields" valueType="table"/>
            <property name="aggregatedFunction" value="" valueType="string"/>
            <property name="isCountFieldFor" valueType="url"/>
            <property name="displayFormat" value="" valueType="string"/>
            <property name="showSubtotal" value="false" valueType="boolean"/>
            <property name="isHidden" value="false" valueType="boolean"/>
            <property name="defaultInstanceKeyValueFormula" valueType="object">
                <object type="ASLExpression" version="1.0">
                    <property name="expression" valueType="table"/>
                </object>
            </property>
        </object>
        <object type="DataSource:field" version="3.0">
            <property name="id" value="f22d03bd-4fab-4607-93a1-be383ef19fb7" valueType="string"/>
            <property name="name" value="XOSTU1" valueType="string"/>
            <property name="description" value="XOSTU1" valueType="string"/>
            <property name="title" value="" valueType="string"/>
            <property name="type" value="VARCHAR" valueType="string"/>
            <property name="size" value="20" valueType="integer"/>
            <property name="allowNulls" value="false" valueType="boolean"/>
            <property name="allowDefault" value="true" valueType="boolean"/>
            <property name="isAutoUniqueId" value="false" valueType="boolean"/>
            <property name="defaultValue" value="''" valueType="string"/>
            <property name="syntheticContent" valueType="table"/>
            <property name="lookupSource" valueType="url"/>
            <property name="parentFields" valueType="table"/>
            <property name="aggregatedFunction" value="" valueType="string"/>
            <property name="isCountFieldFor" valueType="url"/>
            <property name="displayFormat" value="" valueType="string"/>
            <property name="showSubtotal" value="false" valueType="boolean"/>
            <property name="isHidden" value="false" valueType="boolean"/>
            <property name="defaultInstanceKeyValueFormula" valueType="object">
                <object type="ASLExpression" version="1.0">
                    <property name="expression" valueType="table"/>
                </object>
            </property>
        </object>
        <object type="DataSource:field" version="3.0">
            <property name="id" value="35390fed-d963-4b08-9f1f-970a2c458337" valueType="string"/>
            <property name="name" value="XOSTU2" valueType="string"/>
            <property name="description" value="XOSTU2" valueType="string"/>
            <property name="title" value="" valueType="string"/>
            <property name="type" value="VARCHAR" valueType="string"/>
            <property name="size" value="20" valueType="integer"/>
            <property name="allowNulls" value="false" valueType="boolean"/>
            <property name="allowDefault" value="true" valueType="boolean"/>
            <property name="isAutoUniqueId" value="false" valueType="boolean"/>
            <property name="defaultValue" value="''" valueType="string"/>
            <property name="syntheticContent" valueType="table"/>
            <property name="lookupSource" valueType="url"/>
            <property name="parentFields" valueType="table"/>
            <property name="aggregatedFunction" value="" valueType="string"/>
            <property name="isCountFieldFor" valueType="url"/>
            <property name="displayFormat" value="" valueType="string"/>
            <property name="showSubtotal" value="false" valueType="boolean"/>
            <property name="isHidden" value="false" valueType="boolean"/>
            <property name="defaultInstanceKeyValueFormula" valueType="object">
                <object type="ASLExpression" version="1.0">
                    <property name="expression" valueType="table"/>
                </object>
            </property>
        </object>
        <object type="DataSource:field" version="3.0">
            <property name="id" value="d95ce3a3-a975-4476-897e-e2579dffba7a" valueType="string"/>
            <property name="name" value="XOSC02" valueType="string"/>
            <property name="description" value="XOSC02" valueType="string"/>
            <property name="title" value="" valueType="string"/>
            <property name="type" value="INTEGER" valueType="string"/>
            <property name="allowNulls" value="false" valueType="boolean"/>
            <property name="allowDefault" value="true" valueType="boolean"/>
            <property name="defaultValue" value="0" valueType="string"/>
            <property name="syntheticContent" valueType="table"/>
            <property name="lookupSource" valueType="url"/>
            <property name="parentFields" valueType="table"/>
            <property name="aggregatedFunction" value="" valueType="string"/>
            <property name="isCountFieldFor" valueType="url"/>
            <property name="displayFormat" value="" valueType="string"/>
            <property name="showSubtotal" value="false" valueType="boolean"/>
            <property name="isHidden" value="false" valueType="boolean"/>
            <property name="defaultInstanceKeyValueFormula" valueType="object">
                <object type="ASLExpression" version="1.0">
                    <property name="expression" valueType="table"/>
                </object>
            </property>
        </object>
        <object type="DataSource:field" version="3.0">
            <property name="id" value="7cc9fade-20a0-4fc9-a71f-b3479a0a56bf" valueType="string"/>
            <property name="name" value="XOSC01" valueType="string"/>
            <property name="description" value="XOSC01" valueType="string"/>
            <property name="title" value="" valueType="string"/>
            <property name="type" value="INTEGER" valueType="string"/>
            <property name="allowNulls" value="false" valueType="boolean"/>
            <property name="allowDefault" value="true" valueType="boolean"/>
            <property name="defaultValue" value="0" valueType="string"/>
            <property name="syntheticContent" valueType="table"/>
            <property name="lookupSource" valueType="url"/>
            <property name="parentFields" valueType="table"/>
            <property name="aggregatedFunction" value="" valueType="string"/>
            <property name="isCountFieldFor" valueType="url"/>
            <property name="displayFormat" value="" valueType="string"/>
            <property name="showSubtotal" value="false" valueType="boolean"/>
            <property name="isHidden" value="false" valueType="boolean"/>
            <property name="defaultInstanceKeyValueFormula" valueType="object">
                <object type="ASLExpression" version="1.0">
                    <property name="expression" valueType="table"/>
                </object>
            </property>
        </object>
        <object type="DataSource:field" version="3.0">
            <property name="id" value="2e73d96c-a37e-4641-8dde-c956e38bcc40" valueType="string"/>
            <property name="name" value="XOSA01" valueType="string"/>
            <property name="description" value="XOSA01" valueType="string"/>
            <property name="title" value="" valueType="string"/>
            <property name="type" value="FLOAT" valueType="string"/>
            <property name="allowNulls" value="false" valueType="boolean"/>
            <property name="allowDefault" value="true" valueType="boolean"/>
            <property name="defaultValue" value="0" valueType="string"/>
            <property name="syntheticContent" valueType="table"/>
            <property name="lookupSource" valueType="url"/>
            <property name="parentFields" valueType="table"/>
            <property name="aggregatedFunction" value="" valueType="string"/>
            <property name="isCountFieldFor" valueType="url"/>
            <property name="displayFormat" value="" valueType="string"/>
            <property name="showSubtotal" value="false" valueType="boolean"/>
            <property name="isHidden" value="false" valueType="boolean"/>
            <property name="defaultInstanceKeyValueFormula" valueType="object">
                <object type="ASLExpression" version="1.0">
                    <property name="expression" valueType="table"/>
                </object>
            </property>
        </object>
        <object type="DataSource:field" version="3.0">
            <property name="id" value="0cbc845b-b41c-45aa-9047-48774c6fcb95" valueType="string"/>
            <property name="name" value="XOSA02" valueType="string"/>
            <property name="description" value="XOSA02" valueType="string"/>
            <property name="title" value="" valueType="string"/>
            <property name="type" value="FLOAT" valueType="string"/>
            <property name="allowNulls" value="false" valueType="boolean"/>
            <property name="allowDefault" value="true" valueType="boolean"/>
            <property name="defaultValue" value="0" valueType="string"/>
            <property name="syntheticContent" valueType="table"/>
            <property name="lookupSource" valueType="url"/>
            <property name="parentFields" valueType="table"/>
            <property name="aggregatedFunction" value="" valueType="string"/>
            <property name="isCountFieldFor" valueType="url"/>
            <property name="displayFormat" value="" valueType="string"/>
            <property name="showSubtotal" value="false" valueType="boolean"/>
            <property name="isHidden" value="false" valueType="boolean"/>
            <property name="defaultInstanceKeyValueFormula" valueType="object">
                <object type="ASLExpression" version="1.0">
                    <property name="expression" valueType="table"/>
                </object>
            </property>
        </object>
        <object type="DataSource:field" version="3.0">
            <property name="id" value="a3b841d6-5310-4552-a450-fe4e96556a7d" valueType="string"/>
            <property name="name" value="XOSD01" valueType="string"/>
            <property name="description" value="XOSD01" valueType="string"/>
            <property name="title" value="" valueType="string"/>
            <property name="type" value="INTEGER" valueType="string"/>
            <property name="allowNulls" value="false" valueType="boolean"/>
            <property name="allowDefault" value="true" valueType="boolean"/>
            <property name="defaultValue" value="0" valueType="string"/>
            <property name="syntheticContent" valueType="table"/>
            <property name="lookupSource" valueType="url"/>
            <property name="parentFields" valueType="table"/>
            <property name="aggregatedFunction" value="" valueType="string"/>
            <property name="isCountFieldFor" valueType="url"/>
            <property name="displayFormat" value="" valueType="string"/>
            <property name="showSubtotal" value="false" valueType="boolean"/>
            <property name="isHidden" value="false" valueType="boolean"/>
            <property name="defaultInstanceKeyValueFormula" valueType="object">
                <object type="ASLExpression" version="1.0">
                    <property name="expression" valueType="table"/>
                </object>
            </property>
        </object>
        <object type="DataSource:field" version="3.0">
            <property name="id" value="2e56bae0-ee1e-4088-91cd-98673016a2d6" valueType="string"/>
            <property name="name" value="XOSD02" valueType="string"/>
            <property name="description" value="XOSD02" valueType="string"/>
            <property name="title" value="" valueType="string"/>
            <property name="type" value="INTEGER" valueType="string"/>
            <property name="allowNulls" value="false" valueType="boolean"/>
            <property name="allowDefault" value="true" valueType="boolean"/>
            <property name="defaultValue" value="0" valueType="string"/>
            <property name="syntheticContent" valueType="table"/>
            <property name="lookupSource" valueType="url"/>
            <property name="parentFields" valueType="table"/>
            <property name="aggregatedFunction" value="" valueType="string"/>
            <property name="isCountFieldFor" valueType="url"/>
            <property name="displayFormat" value="" valueType="string"/>
            <property name="showSubtotal" value="false" valueType="boolean"/>
            <property name="isHidden" value="false" valueType="boolean"/>
            <property name="defaultInstanceKeyValueFormula" valueType="object">
                <object type="ASLExpression" version="1.0">
                    <property name="expression" valueType="table"/>
                </object>
            </property>
        </object>
        <object type="DataSource:field" version="3.0">
            <property name="id" value="f1d0a6a4-a1ab-4e69-84ba-5c9a04eab946" valueType="string"/>
            <property name="name" value="XOSU01" valueType="string"/>
            <property name="description" value="XOSU01" valueType="string"/>
            <property name="title" value="" valueType="string"/>
            <property name="type" value="VARCHAR" valueType="string"/>
            <property name="size" value="50" valueType="integer"/>
            <property name="allowNulls" value="false" valueType="boolean"/>
            <property name="allowDefault" value="true" valueType="boolean"/>
            <property name="isAutoUniqueId" value="false" valueType="boolean"/>
            <property name="defaultValue" value="''" valueType="string"/>
            <property name="syntheticContent" valueType="table"/>
            <property name="lookupSource" valueType="url"/>
            <property name="parentFields" valueType="table"/>
            <property name="aggregatedFunction" value="" valueType="string"/>
            <property name="isCountFieldFor" valueType="url"/>
            <property name="displayFormat" value="" valueType="string"/>
            <property name="showSubtotal" value="false" valueType="boolean"/>
            <property name="isHidden" value="false" valueType="boolean"/>
            <property name="defaultInstanceKeyValueFormula" valueType="object">
                <object type="ASLExpression" version="1.0">
                    <property name="expression" valueType="table"/>
                </object>
            </property>
        </object>
        <object type="DataSource:field" version="3.0">
            <property name="id" value="c5624dc3-4f7c-4a81-9bcb-4dd08bc35907" valueType="string"/>
            <property name="name" value="XOSU02" valueType="string"/>
            <property name="description" value="XOSU02" valueType="string"/>
            <property name="title" value="" valueType="string"/>
            <property name="type" value="VARCHAR" valueType="string"/>
            <property name="size" value="50" valueType="integer"/>
            <property name="allowNulls" value="false" valueType="boolean"/>
            <property name="allowDefault" value="true" valueType="boolean"/>
            <property name="isAutoUniqueId" value="false" valueType="boolean"/>
            <property name="defaultValue" value="''" valueType="string"/>
            <property name="syntheticContent" valueType="table"/>
            <property name="lookupSource" valueType="url"/>
            <property name="parentFields" valueType="table"/>
            <property name="aggregatedFunction" value="" valueType="string"/>
            <property name="isCountFieldFor" valueType="url"/>
            <property name="displayFormat" value="" valueType="string"/>
            <property name="showSubtotal" value="false" valueType="boolean"/>
            <property name="isHidden" value="false" valueType="boolean"/>
            <property name="defaultInstanceKeyValueFormula" valueType="object">
                <object type="ASLExpression" version="1.0">
                    <property name="expression" valueType="table"/>
                </object>
            </property>
        </object>
        <object type="DataSource:field" version="3.0">
            <property name="id" value="0673e9ec-3dc8-4ea9-80b3-17dbd3b099f3" valueType="string"/>
            <property name="name" value="XOENDT" valueType="string"/>
            <property name="description" value="Fecha de ingreso al sistema" valueType="string"/>
            <property name="title" value="" valueType="string"/>
            <property name="type" value="VARCHAR" valueType="string"/>
            <property name="size" value="10" valueType="integer"/>
            <property name="allowNulls" value="false" valueType="boolean"/>
            <property name="allowDefault" value="true" valueType="boolean"/>
            <property name="isAutoUniqueId" value="false" valueType="boolean"/>
            <property name="defaultValue" value="''" valueType="string"/>
            <property name="syntheticContent" valueType="table"/>
            <property name="lookupSource" valueType="url"/>
            <property name="parentFields" valueType="table"/>
            <property name="aggregatedFunction" value="" valueType="string"/>
            <property name="isCountFieldFor" valueType="url"/>
            <property name="displayFormat" value="" valueType="string"/>
            <property name="showSubtotal" value="false" valueType="boolean"/>
            <property name="isHidden" value="false" valueType="boolean"/>
            <property name="defaultInstanceKeyValueFormula" valueType="object">
                <object type="ASLExpression" version="1.0">
                    <property name="expression" valueType="table"/>
                </object>
            </property>
        </object>
        <object type="DataSource:field" version="3.0">
            <property name="id" value="ce7b052d-5d44-465b-8620-9fd13da7a9e7" valueType="string"/>
            <property name="name" value="AX_XONOTX" valueType="string"/>
            <property name="description" value="NIT (#Documento Cliente)" valueType="string"/>
            <property name="title" value="" valueType="string"/>
            <property name="type" value="VARCHAR" valueType="string"/>
            <property name="size" value="15" valueType="integer"/>
            <property name="allowNulls" value="true" valueType="boolean"/>
            <property name="allowDefault" value="false" valueType="boolean"/>
            <property name="isAutoUniqueId" value="false" valueType="boolean"/>
            <property name="syntheticContent" valueType="table"/>
            <property name="lookupSource" valueType="url"/>
            <property name="parentFields" valueType="table"/>
            <property name="aggregatedFunction" value="" valueType="string"/>
            <property name="isCountFieldFor" valueType="url"/>
            <property name="displayFormat" value="" valueType="string"/>
            <property name="showSubtotal" value="false" valueType="boolean"/>
            <property name="isHidden" value="false" valueType="boolean"/>
            <property name="defaultInstanceKeyValueFormula" valueType="object">
                <object type="ASLExpression" version="1.0">
                    <property name="expression" valueType="table"/>
                </object>
            </property>
        </object>
        <object type="DataSource:field" version="3.0">
            <property name="id" value="aac44ea9-d52c-413b-b33e-2d93128275a4" valueType="string"/>
            <property name="name" value="AX_XOENDT" valueType="string"/>
            <property name="description" value="AX_XOENDT - Fecha de ingreso al sistema" valueType="string"/>
            <property name="title" value="" valueType="string"/>
            <property name="type" value="DATE" valueType="string"/>
            <property name="allowNulls" value="false" valueType="boolean"/>
            <property name="allowDefault" value="true" valueType="boolean"/>
            <property name="defaultValue" value="{ts '1990-01-01 00:00:00'}" valueType="string"/>
            <property name="syntheticContent" valueType="table"/>
            <property name="lookupSource" valueType="url"/>
            <property name="parentFields" valueType="table"/>
            <property name="aggregatedFunction" value="" valueType="string"/>
            <property name="isCountFieldFor" valueType="url"/>
            <property name="displayFormat" value="" valueType="string"/>
            <property name="showSubtotal" value="false" valueType="boolean"/>
            <property name="isHidden" value="false" valueType="boolean"/>
            <property name="defaultInstanceKeyValueFormula" valueType="object">
                <object type="ASLExpression" version="1.0">
                    <property name="expression" valueType="table"/>
                </object>
            </property>
        </object>
        <object type="DataSource:field" version="3.0">
            <property name="id" value="a4d9cd3d-43ac-4f64-a75b-14da181e51fd" valueType="string"/>
            <property name="name" value="AX_XONOCO" valueType="string"/>
            <property name="description" value="Número de Garantía" valueType="string"/>
            <property name="title" value="" valueType="string"/>
            <property name="type" value="VARCHAR" valueType="string"/>
            <property name="size" value="30" valueType="integer"/>
            <property name="allowNulls" value="false" valueType="boolean"/>
            <property name="allowDefault" value="true" valueType="boolean"/>
            <property name="isAutoUniqueId" value="false" valueType="boolean"/>
            <property name="defaultValue" value="''" valueType="string"/>
            <property name="syntheticContent" valueType="table"/>
            <property name="lookupSource" valueType="url"/>
            <property name="parentFields" valueType="table"/>
            <property name="aggregatedFunction" value="" valueType="string"/>
            <property name="isCountFieldFor" valueType="url"/>
            <property name="displayFormat" value="" valueType="string"/>
            <property name="showSubtotal" value="false" valueType="boolean"/>
            <property name="isHidden" value="false" valueType="boolean"/>
            <property name="defaultInstanceKeyValueFormula" valueType="object">
                <object type="ASLExpression" version="1.0">
                    <property name="expression" valueType="table"/>
                </object>
            </property>
        </object>
        <object type="DataSource:field" version="3.0">
            <property name="id" value="01645d89-7639-43cf-87b2-b3590164dc8b" valueType="string"/>
            <property name="name" value="entity" valueType="string"/>
            <property name="description" value="" valueType="string"/>
            <property name="title" value="" valueType="string"/>
            <property name="type" value="VARCHAR" valueType="string"/>
            <property name="size" value="30" valueType="integer"/>
            <property name="allowNulls" value="true" valueType="boolean"/>
            <property name="allowDefault" value="true" valueType="boolean"/>
            <property name="isAutoUniqueId" value="false" valueType="boolean"/>
            <property name="defaultValue" value="'Banco'" valueType="string"/>
            <property name="syntheticContent" valueType="table"/>
            <property name="lookupSource" valueType="url"/>
            <property name="parentFields" valueType="table"/>
            <property name="aggregatedFunction" value="" valueType="string"/>
            <property name="isCountFieldFor" valueType="url"/>
            <property name="displayFormat" value="" valueType="string"/>
            <property name="showSubtotal" value="false" valueType="boolean"/>
            <property name="isHidden" value="false" valueType="boolean"/>
            <property name="defaultInstanceKeyValueFormula" valueType="object">
                <object type="ASLExpression" version="1.0">
                    <property name="expression" valueType="table"/>
                </object>
            </property>
        </object>
        <object type="DataSource:field" version="3.0">
            <property name="id" value="3b7c221c-53ac-4d9b-a6c2-8e90648c866c" valueType="string"/>
            <property name="name" value="loaded_on" valueType="string"/>
            <property name="description" value="Loaded on" valueType="string"/>
            <property name="title" value="" valueType="string"/>
            <property name="type" value="DATE" valueType="string"/>
            <property name="allowNulls" value="false" valueType="boolean"/>
            <property name="allowDefault" value="true" valueType="boolean"/>
            <property name="defaultValue" value="sysdate" valueType="string"/>
            <property name="syntheticContent" valueType="table"/>
            <property name="lookupSource" valueType="url"/>
            <property name="parentFields" valueType="table"/>
            <property name="aggregatedFunction" value="" valueType="string"/>
            <property name="isCountFieldFor" valueType="url"/>
            <property name="displayFormat" value="" valueType="string"/>
            <property name="showSubtotal" value="false" valueType="boolean"/>
            <property name="isHidden" value="false" valueType="boolean"/>
            <property name="defaultInstanceKeyValueFormula" valueType="object">
                <object type="ASLExpression" version="1.0">
                    <property name="expression" valueType="table"/>
                </object>
            </property>
        </object>
        <object type="DataSource:field" version="3.0">
            <property name="id" value="8827003a-8222-4abb-a497-c9946a59b3bc" valueType="string"/>
            <property name="name" value="source_name" valueType="string"/>
            <property name="description" value="Nombre De Fuente" valueType="string"/>
            <property name="title" value="" valueType="string"/>
            <property name="type" value="VARCHAR" valueType="string"/>
            <property name="size" value="30" valueType="integer"/>
            <property name="allowNulls" value="true" valueType="boolean"/>
            <property name="allowDefault" value="true" valueType="boolean"/>
            <property name="isAutoUniqueId" value="false" valueType="boolean"/>
            <property name="defaultValue" value="'VISIONR_CEXOWBN'" valueType="string"/>
            <property name="syntheticContent" valueType="table"/>
            <property name="lookupSource" valueType="url"/>
            <property name="parentFields" valueType="table"/>
            <property name="aggregatedFunction" value="" valueType="string"/>
            <property name="isCountFieldFor" valueType="url"/>
            <property name="displayFormat" value="" valueType="string"/>
            <property name="showSubtotal" value="false" valueType="boolean"/>
            <property name="isHidden" value="false" valueType="boolean"/>
            <property name="defaultInstanceKeyValueFormula" valueType="object">
                <object type="ASLExpression" version="1.0">
                    <property name="expression" valueType="table"/>
                </object>
            </property>
        </object>
    </property>
    <property name="keyFields" valueType="table">
        <object type="DataSource:localFieldReference" version="1.0">
            <property name="value" valueType="url">DataSource[this].layout["axiom_index"{445fb14b-a764-4930-b883-bd0fef571ddd}]</property>
        </object>
    </property>
    <property name="index" valueType="table">
        <object type="DataSource:index" version="1.0">
            <property name="clustered" value="false" valueType="boolean"/>
            <property name="unique" value="false" valueType="boolean"/>
            <property name="fields" valueType="table">
                <object type="DataSource:localFieldReference" version="1.0">
                    <property name="value" valueType="url">DataSource[this].layout["XOCDOB"{6cdc2477-692f-44c0-a0fe-a2ecc0b8e53a}]</property>
                </object>
            </property>
        </object>
        <object type="DataSource:index" version="1.0">
            <property name="clustered" value="false" valueType="boolean"/>
            <property name="unique" value="false" valueType="boolean"/>
            <property name="fields" valueType="table">
                <object type="DataSource:localFieldReference" version="1.0">
                    <property name="value" valueType="url">DataSource[this].layout["XONOCO"{b22d9165-8d56-43ff-9ec5-1fcbfc07260e}]</property>
                </object>
            </property>
        </object>
        <object type="DataSource:index" version="1.0">
            <property name="clustered" value="false" valueType="boolean"/>
            <property name="unique" value="false" valueType="boolean"/>
            <property name="fields" valueType="table">
                <object type="DataSource:localFieldReference" version="1.0">
                    <property name="value" valueType="url">DataSource[this].layout["XONAMK"{986d4e96-9ae4-402c-a0bb-ba2dc026c1a8}]</property>
                </object>
            </property>
        </object>
        <object type="DataSource:index" version="1.0">
            <property name="clustered" value="false" valueType="boolean"/>
            <property name="unique" value="false" valueType="boolean"/>
            <property name="fields" valueType="table">
                <object type="DataSource:localFieldReference" version="1.0">
                    <property name="value" valueType="url">DataSource[this].layout["AX_XONOCO"{a4d9cd3d-43ac-4f64-a75b-14da181e51fd}]</property>
                </object>
            </property>
        </object>
    </property>
    <property name="createIndexOnKeyFields" value="true" valueType="boolean"/>
    <property name="indexOnKeyFieldsClustered" value="true" valueType="boolean"/>
    <property name="storageType" value="CONTINUOUS_PARTITION" valueType="string"/>
    <property name="internalSourceTablePrefix" value="CEXOWBN_" valueType="string"/>
    <property name="asOfDateField" valueType="url">DataSource[this].layout["asof_date"{56bb12ba-0cb7-48d2-b13e-40cc6072e690}]</property>
    <property name="instanceKeys" valueType="table">
        <object type="DataSource:localFieldReference" version="1.0">
            <property name="value" valueType="url">DataSource[this].layout["version"{c2029dac-42ca-419d-8cc4-639c657ceb0d}]</property>
        </object>
        <object type="DataSource:localFieldReference" version="1.0">
            <property name="value" valueType="url">DataSource[this].layout["filing_version"{7a55b0a9-8f3f-4d16-be9a-cf2d2f3a206b}]</property>
        </object>
    </property>
    <property name="postTableCreationStatements" valueType="table"/>
    <property name="postAdjustmentTableCreationStatements" valueType="table"/>
    <property name="keyVariables" valueType="table"/>
    <property name="nonKeyVariables" valueType="table"/>
    <property name="computeStatistics" value="NONE" valueType="string"/>
    <property name="validations" valueType="table"/>
    <property name="fourEyesCheck" value="false" valueType="boolean"/>
    <property name="readOnlyAdjustment" value="false" valueType="boolean"/>
    <property name="freezeLevel" value="1" valueType="integer"/>
    <property name="instanceRebuildRestriction" value="AlterFullRebuild" valueType="string"/>
    <property name="loaders" valueType="table">
        <object type="DataSource:scenario" version="3.0">
            <property name="id" value="5abac81d-8156-49d8-b0fb-0abc25d21eb3" valueType="string"/>
            <property name="name" value="New_Scenario_1" valueType="string"/>
            <property name="loaderType" value="tableLoader" valueType="string"/>
            <property name="keepTableContent" value="false" valueType="boolean"/>
            <property name="parameters" valueType="object">
                <object type="TableLoaderParameters" version="2.0">
                    <property name="loaderEnumerationField" valueType="object">
                        <object type="DataSource:localFieldReference" version="1.0">
                            <property name="value" valueType="url">DataSource[this].layout["axiom_index"{445fb14b-a764-4930-b883-bd0fef571ddd}]</property>
                        </object>
                    </property>
                    <property name="loaderSelectDistinct" value="false" valueType="boolean"/>
                    <property name="loaderCondition" valueType="table"/>
                    <property name="dbSourceToLoadFrom" valueType="url">DBSource["BANKVISION_NACIONAL_VISIONR"{ad5dc5bb-1a09-4db2-aaec-adfb0f68a49f}]</property>
                    <property name="tableLoadingMethod" value="direct" valueType="string"/>
                    <property name="loaderConfigFields" valueType="table">
                        <object type="TableLoaderParameters:loaderConfigField" version="1.0">
                            <property name="sourceField" valueType="object">
                                <object type="DataSource:localFieldReference" version="1.0">
                                    <property name="value" valueType="url">DataSource[this].layout["XONOCO"{b22d9165-8d56-43ff-9ec5-1fcbfc07260e}]</property>
                                </object>
                            </property>
                            <property name="origColumn" value="xonoco" valueType="string"/>
                            <property name="format" value="" valueType="string"/>
                            <property name="position" value="" valueType="string"/>
                        </object>
                        <object type="TableLoaderParameters:loaderConfigField" version="1.0">
                            <property name="sourceField" valueType="object">
                                <object type="DataSource:localFieldReference" version="1.0">
                                    <property name="value" valueType="url">DataSource[this].layout["XOCDOB"{6cdc2477-692f-44c0-a0fe-a2ecc0b8e53a}]</property>
                                </object>
                            </property>
                            <property name="origColumn" value="xocdob" valueType="string"/>
                            <property name="format" value="" valueType="string"/>
                            <property name="position" value="" valueType="string"/>
                        </object>
                        <object type="TableLoaderParameters:loaderConfigField" version="1.0">
                            <property name="sourceField" valueType="object">
                                <object type="DataSource:localFieldReference" version="1.0">
                                    <property name="value" valueType="url">DataSource[this].layout["XONOTX"{1b416f18-3ec6-426c-89ae-49a29bea5095}]</property>
                                </object>
                            </property>
                            <property name="origColumn" value="xonotx" valueType="string"/>
                            <property name="format" value="" valueType="string"/>
                            <property name="position" value="" valueType="string"/>
                        </object>
                        <object type="TableLoaderParameters:loaderConfigField" version="1.0">
                            <property name="sourceField" valueType="object">
                                <object type="DataSource:localFieldReference" version="1.0">
                                    <property name="value" valueType="url">DataSource[this].layout["XONAMK"{986d4e96-9ae4-402c-a0bb-ba2dc026c1a8}]</property>
                                </object>
                            </property>
                            <property name="origColumn" value="xonamk" valueType="string"/>
                            <property name="format" value="" valueType="string"/>
                            <property name="position" value="" valueType="string"/>
                        </object>
                        <object type="TableLoaderParameters:loaderConfigField" version="1.0">
                            <property name="sourceField" valueType="object">
                                <object type="DataSource:localFieldReference" version="1.0">
                                    <property name="value" valueType="url">DataSource[this].layout["XOPP01"{5595194f-9b77-4686-824e-471a724c3b5f}]</property>
                                </object>
                            </property>
                            <property name="origColumn" value="xopp01" valueType="string"/>
                            <property name="format" value="" valueType="string"/>
                            <property name="position" value="" valueType="string"/>
                        </object>
                        <object type="TableLoaderParameters:loaderConfigField" version="1.0">
                            <property name="sourceField" valueType="object">
                                <object type="DataSource:localFieldReference" version="1.0">
                                    <property name="value" valueType="url">DataSource[this].layout["XAMTNU"{3ed75ab1-c71d-4280-a4a6-caba2940e4f5}]</property>
                                </object>
                            </property>
                            <property name="origColumn" value="xamtnu" valueType="string"/>
                            <property name="format" value="" valueType="string"/>
                            <property name="position" value="" valueType="string"/>
                        </object>
                        <object type="TableLoaderParameters:loaderConfigField" version="1.0">
                            <property name="sourceField" valueType="object">
                                <object type="DataSource:localFieldReference" version="1.0">
                                    <property name="value" valueType="url">DataSource[this].layout["XAMTUS"{841be33d-458a-4c65-a1a6-3da9f56ce641}]</property>
                                </object>
                            </property>
                            <property name="origColumn" value="xamtus" valueType="string"/>
                            <property name="format" value="" valueType="string"/>
                            <property name="position" value="" valueType="string"/>
                        </object>
                        <object type="TableLoaderParameters:loaderConfigField" version="1.0">
                            <property name="sourceField" valueType="object">
                                <object type="DataSource:localFieldReference" version="1.0">
                                    <property name="value" valueType="url">DataSource[this].layout["XOSTU1"{f22d03bd-4fab-4607-93a1-be383ef19fb7}]</property>
                                </object>
                            </property>
                            <property name="origColumn" value="xostu1" valueType="string"/>
                            <property name="format" value="" valueType="string"/>
                            <property name="position" value="" valueType="string"/>
                        </object>
                        <object type="TableLoaderParameters:loaderConfigField" version="1.0">
                            <property name="sourceField" valueType="object">
                                <object type="DataSource:localFieldReference" version="1.0">
                                    <property name="value" valueType="url">DataSource[this].layout["XOSTU2"{35390fed-d963-4b08-9f1f-970a2c458337}]</property>
                                </object>
                            </property>
                            <property name="origColumn" value="xostu2" valueType="string"/>
                            <property name="format" value="" valueType="string"/>
                            <property name="position" value="" valueType="string"/>
                        </object>
                        <object type="TableLoaderParameters:loaderConfigField" version="1.0">
                            <property name="sourceField" valueType="object">
                                <object type="DataSource:localFieldReference" version="1.0">
                                    <property name="value" valueType="url">DataSource[this].layout["XOSC02"{d95ce3a3-a975-4476-897e-e2579dffba7a}]</property>
                                </object>
                            </property>
                            <property name="origColumn" value="xosc02" valueType="string"/>
                            <property name="format" value="" valueType="string"/>
                            <property name="position" value="" valueType="string"/>
                        </object>
                        <object type="TableLoaderParameters:loaderConfigField" version="1.0">
                            <property name="sourceField" valueType="object">
                                <object type="DataSource:localFieldReference" version="1.0">
                                    <property name="value" valueType="url">DataSource[this].layout["XOSC01"{7cc9fade-20a0-4fc9-a71f-b3479a0a56bf}]</property>
                                </object>
                            </property>
                            <property name="origColumn" value="xosc01" valueType="string"/>
                            <property name="format" value="" valueType="string"/>
                            <property name="position" value="" valueType="string"/>
                        </object>
                        <object type="TableLoaderParameters:loaderConfigField" version="1.0">
                            <property name="sourceField" valueType="object">
                                <object type="DataSource:localFieldReference" version="1.0">
                                    <property name="value" valueType="url">DataSource[this].layout["XOSA01"{2e73d96c-a37e-4641-8dde-c956e38bcc40}]</property>
                                </object>
                            </property>
                            <property name="origColumn" value="xosa01" valueType="string"/>
                            <property name="format" value="" valueType="string"/>
                            <property name="position" value="" valueType="string"/>
                        </object>
                        <object type="TableLoaderParameters:loaderConfigField" version="1.0">
                            <property name="sourceField" valueType="object">
                                <object type="DataSource:localFieldReference" version="1.0">
                                    <property name="value" valueType="url">DataSource[this].layout["XOSA02"{0cbc845b-b41c-45aa-9047-48774c6fcb95}]</property>
                                </object>
                            </property>
                            <property name="origColumn" value="xosa02" valueType="string"/>
                            <property name="format" value="" valueType="string"/>
                            <property name="position" value="" valueType="string"/>
                        </object>
                        <object type="TableLoaderParameters:loaderConfigField" version="1.0">
                            <property name="sourceField" valueType="object">
                                <object type="DataSource:localFieldReference" version="1.0">
                                    <property name="value" valueType="url">DataSource[this].layout["XOSD01"{a3b841d6-5310-4552-a450-fe4e96556a7d}]</property>
                                </object>
                            </property>
                            <property name="origColumn" value="xosd01" valueType="string"/>
                            <property name="format" value="" valueType="string"/>
                            <property name="position" value="" valueType="string"/>
                        </object>
                        <object type="TableLoaderParameters:loaderConfigField" version="1.0">
                            <property name="sourceField" valueType="object">
                                <object type="DataSource:localFieldReference" version="1.0">
                                    <property name="value" valueType="url">DataSource[this].layout["XOSD02"{2e56bae0-ee1e-4088-91cd-98673016a2d6}]</property>
                                </object>
                            </property>
                            <property name="origColumn" value="xosd02" valueType="string"/>
                            <property name="format" value="" valueType="string"/>
                            <property name="position" value="" valueType="string"/>
                        </object>
                        <object type="TableLoaderParameters:loaderConfigField" version="1.0">
                            <property name="sourceField" valueType="object">
                                <object type="DataSource:localFieldReference" version="1.0">
                                    <property name="value" valueType="url">DataSource[this].layout["XOSU01"{f1d0a6a4-a1ab-4e69-84ba-5c9a04eab946}]</property>
                                </object>
                            </property>
                            <property name="origColumn" value="xosu01" valueType="string"/>
                            <property name="format" value="" valueType="string"/>
                            <property name="position" value="" valueType="string"/>
                        </object>
                        <object type="TableLoaderParameters:loaderConfigField" version="1.0">
                            <property name="sourceField" valueType="object">
                                <object type="DataSource:localFieldReference" version="1.0">
                                    <property name="value" valueType="url">DataSource[this].layout["XOSU02"{c5624dc3-4f7c-4a81-9bcb-4dd08bc35907}]</property>
                                </object>
                            </property>
                            <property name="origColumn" value="xosu02" valueType="string"/>
                            <property name="format" value="" valueType="string"/>
                            <property name="position" value="" valueType="string"/>
                        </object>
                    </property>
                    <property name="loadingStatement" value="APPEND" valueType="string"/>
                </object>
            </property>
            <property name="loaderActions" valueType="table">
                <object type="LoaderAction:actionCombine" version="2.0">
                    <property name="id" value="089edb84-bdb3-4092-b368-a16b74ca88b9" valueType="string"/>
                    <property name="column" valueType="object">
                        <object type="DataSource:localFieldReference" version="1.0">
                            <property name="value" valueType="url">DataSource[this].layout["AX_XONOCO"{a4d9cd3d-43ac-4f64-a75b-14da181e51fd}]</property>
                        </object>
                    </property>
                    <property name="expression" valueType="table">
                        <object type="SQLExpressionPart" version="1.0">
                            <property name="value" value="to_char(xonoco)" valueType="string"/>
                        </object>
                    </property>
                </object>
                <object type="LoaderAction:actionStatement" version="2.0">
                    <property name="id" value="55f85583-9acc-465e-aa24-329bd9101c22" valueType="string"/>
                    <property name="statement" valueType="table">
                        <object type="SQLExpressionPart" version="1.0">
                            <property name="value" value="UPDATE " valueType="string"/>
                        </object>
                        <object type="SQLConstant" version="1.0">
                            <property name="name" value="table_name" valueType="string"/>
                        </object>
                        <object type="SQLExpressionPart" version="1.0">
                            <property name="value" value=" &#xa;SET AX_XONOTX = TO_CHAR(TO_NUMBER(TRIM(XONOTX)))  ,&#xa;AX_XOENDT =&#xa;CASE&#xa;        WHEN length(XOENDT) = 8 THEN to_date(XOENDT, 'yyyymmdd')&#xa;        ELSE to_date('19000101', 'yyyymmdd')&#xa;END " valueType="string"/>
                        </object>
                    </property>
                </object>
            </property>
            <property name="reapplyAdjustmentsAfterDataLoad" value="false" valueType="boolean"/>
        </object>
    </property>
    <property name="docData" valueType="object">
        <object type="DocData" version="1.0">
            <property name="comment" value="Fecha Creación:  11/08/2020 AxiomSL - lejpuert&#xa;Descripción: Se realiza carga de información de Beneficiarios de Garantías&#xa;-----------------------------------------------------------------------------------------------------------------------------------------------------------------------------------------------------&#xa;" valueType="string"/>
        </object>
    </property>
</object>