<object stamp="2d2a582a-6a57-4e25-870d-3013f41037cf_1657207868680" type="Aggregation" version="7.0">
    <property name="objectId" value="872306b6-06c4-41da-8f30-5cc34a57a7be" valueType="string"/>
    <property name="branchId" value="4d11a90c-cc80-4bd0-9e4e-5d7d712c3675" valueType="string"/>
    <property name="name" value="F_414_FACTORING_PGD_TR" valueType="string"/>
    <property name="description" value="se crea agg con el cruce de infromacion de factoring pagador con la tabla parametrica" valueType="string"/>
    <property name="models" valueType="table">
        <object type="ModelBasedObject:modelEntry" version="1.0">
            <property name="dataModel" valueType="url">DataModel["F_414_FACTORING__PGD_TR"{25e8ebb7-3cad-4363-b464-d40e1e9f2a4c}]</property>
        </object>
    </property>
    <property name="includeNewModelsInExecution" value="true" valueType="boolean"/>
    <property name="nonKeyVariables" valueType="table"/>
    <property name="details" valueType="table">
        <object type="Aggregation:detail" version="1.0">
            <property name="id" value="baf2d342-0fac-4598-8e23-6416609117f0" valueType="string"/>
            <property name="name" value="GNIT" valueType="string"/>
            <property name="description" value="Nit del obligado" valueType="string"/>
            <property name="overrideLookupInformation" value="false" valueType="boolean"/>
            <property name="displayFormat" value="" valueType="string"/>
            <property name="title" value="" valueType="string"/>
            <property name="overrideNullable" value="DEFAULT" valueType="string"/>
        </object>
        <object type="Aggregation:detail" version="1.0">
            <property name="id" value="6897bb33-73e3-46d2-a1b0-f3f124537da0" valueType="string"/>
            <property name="name" value="GDOCTO" valueType="string"/>
            <property name="description" value="Identificador de la obligacion" valueType="string"/>
            <property name="overrideLookupInformation" value="false" valueType="boolean"/>
            <property name="displayFormat" value="" valueType="string"/>
            <property name="title" value="" valueType="string"/>
            <property name="overrideNullable" value="DEFAULT" valueType="string"/>
        </object>
        <object type="Aggregation:detail" version="1.0">
            <property name="id" value="8fad4486-fe7f-4d73-9361-5dc161fb347d" valueType="string"/>
            <property name="name" value="VALUS" valueType="string"/>
            <property name="description" value="Tipo de moneda" valueType="string"/>
            <property name="overrideLookupInformation" value="false" valueType="boolean"/>
            <property name="displayFormat" value="" valueType="string"/>
            <property name="title" value="" valueType="string"/>
            <property name="overrideNullable" value="DEFAULT" valueType="string"/>
        </object>
        <object type="Aggregation:detail" version="1.0">
            <property name="id" value="3d7dcea0-6d43-4901-b8be-b8a01af2da7b" valueType="string"/>
            <property name="name" value="GLINEA" valueType="string"/>
            <property name="description" value="Linea de producto" valueType="string"/>
            <property name="overrideLookupInformation" value="false" valueType="boolean"/>
            <property name="displayFormat" value="" valueType="string"/>
            <property name="title" value="" valueType="string"/>
            <property name="overrideNullable" value="DEFAULT" valueType="string"/>
        </object>
        <object type="Aggregation:detail" version="1.0">
            <property name="id" value="e38617c1-6b65-4319-8886-bc668ef0d7a8" valueType="string"/>
            <property name="name" value="TIPOCREDI" valueType="string"/>
            <property name="description" value="Tipo de Credito" valueType="string"/>
            <property name="overrideLookupInformation" value="false" valueType="boolean"/>
            <property name="displayFormat" value="" valueType="string"/>
            <property name="title" value="" valueType="string"/>
            <property name="overrideNullable" value="DEFAULT" valueType="string"/>
        </object>
        <object type="Aggregation:detail" version="1.0">
            <property name="id" value="a44a5c1e-2c4c-4d47-8a69-8192f1b1f95a" valueType="string"/>
            <property name="name" value="DIANETOR" valueType="string"/>
            <property name="description" value="Dia Anterior" valueType="string"/>
            <property name="overrideLookupInformation" value="false" valueType="boolean"/>
            <property name="displayFormat" value="" valueType="string"/>
            <property name="title" value="" valueType="string"/>
            <property name="overrideNullable" value="DEFAULT" valueType="string"/>
        </object>
        <object type="Aggregation:detail" version="1.0">
            <property name="id" value="fc894e54-eb9b-4178-977f-2aee2d69c59b" valueType="string"/>
            <property name="name" value="TIPOTASA" valueType="string"/>
            <property name="description" value="Tipo de tasa" valueType="string"/>
            <property name="overrideLookupInformation" value="false" valueType="boolean"/>
            <property name="displayFormat" value="" valueType="string"/>
            <property name="title" value="" valueType="string"/>
            <property name="overrideNullable" value="DEFAULT" valueType="string"/>
        </object>
        <object type="Aggregation:detail" version="1.0">
            <property name="id" value="b82c2db2-3785-4cc9-abe6-34c9e5e2f414" valueType="string"/>
            <property name="name" value="FECHACONTA" valueType="string"/>
            <property name="description" value="Fecha contable" valueType="string"/>
            <property name="overrideLookupInformation" value="false" valueType="boolean"/>
            <property name="displayFormat" value="" valueType="string"/>
            <property name="title" value="" valueType="string"/>
            <property name="overrideNullable" value="DEFAULT" valueType="string"/>
        </object>
        <object type="Aggregation:detail" version="1.0">
            <property name="id" value="0bf6af55-e5bb-4375-8eb2-0efbb170b741" valueType="string"/>
            <property name="name" value="ESTADOBLIG" valueType="string"/>
            <property name="description" value="Estado de la obligacion" valueType="string"/>
            <property name="overrideLookupInformation" value="false" valueType="boolean"/>
            <property name="displayFormat" value="" valueType="string"/>
            <property name="title" value="" valueType="string"/>
            <property name="overrideNullable" value="DEFAULT" valueType="string"/>
        </object>
        <object type="Aggregation:detail" version="1.0">
            <property name="id" value="c290354b-6ad6-498b-a53e-208b54c24925" valueType="string"/>
            <property name="name" value="GPLAN" valueType="string"/>
            <property name="description" value="Tipo de plan" valueType="string"/>
            <property name="overrideLookupInformation" value="false" valueType="boolean"/>
            <property name="displayFormat" value="" valueType="string"/>
            <property name="title" value="" valueType="string"/>
            <property name="overrideNullable" value="DEFAULT" valueType="string"/>
        </object>
        <object type="Aggregation:detail" version="1.0">
            <property name="id" value="7ab4b2f3-5260-49dc-a2e5-fb839b5bfcf8" valueType="string"/>
            <property name="name" value="FECHAVENCE_COL" valueType="string"/>
            <property name="description" value="Fecha de vencimimento" valueType="string"/>
            <property name="overrideLookupInformation" value="false" valueType="boolean"/>
            <property name="displayFormat" value="" valueType="string"/>
            <property name="title" value="" valueType="string"/>
            <property name="overrideNullable" value="DEFAULT" valueType="string"/>
        </object>
        <object type="Aggregation:detail" version="1.0">
            <property name="id" value="f46c077a-f972-4dd9-b938-65f90b5fa2e4" valueType="string"/>
            <property name="name" value="FECHAPLICA" valueType="string"/>
            <property name="description" value="Fecha de aplicación" valueType="string"/>
            <property name="overrideLookupInformation" value="false" valueType="boolean"/>
            <property name="displayFormat" value="" valueType="string"/>
            <property name="title" value="" valueType="string"/>
            <property name="overrideNullable" value="DEFAULT" valueType="string"/>
        </object>
        <object type="Aggregation:detail" version="1.0">
            <property name="id" value="d5423c53-9166-4425-a0fc-4d99201403c5" valueType="string"/>
            <property name="name" value="GNIT_NODV" valueType="string"/>
            <property name="description" value="GNIT MODIFICADO" valueType="string"/>
            <property name="overrideLookupInformation" value="false" valueType="boolean"/>
            <property name="displayFormat" value="" valueType="string"/>
            <property name="title" value="" valueType="string"/>
            <property name="overrideNullable" value="DEFAULT" valueType="string"/>
        </object>
        <object type="Aggregation:detail" version="1.0">
            <property name="id" value="364fec5b-b62c-477e-8436-ca0f0d6b71f7" valueType="string"/>
            <property name="name" value="TIPIDEN" valueType="string"/>
            <property name="description" value="Tipo de Identificacion" valueType="string"/>
            <property name="overrideLookupInformation" value="false" valueType="boolean"/>
            <property name="displayFormat" value="" valueType="string"/>
            <property name="title" value="" valueType="string"/>
            <property name="overrideNullable" value="DEFAULT" valueType="string"/>
        </object>
        <object type="Aggregation:detail" version="1.0">
            <property name="id" value="2c547571-7fc4-4c0f-b9e8-f5b32264e05d" valueType="string"/>
            <property name="name" value="CALIF" valueType="string"/>
            <property name="description" value="Calificacion" valueType="string"/>
            <property name="overrideLookupInformation" value="false" valueType="boolean"/>
            <property name="displayFormat" value="" valueType="string"/>
            <property name="title" value="" valueType="string"/>
            <property name="overrideNullable" value="DEFAULT" valueType="string"/>
        </object>
        <object type="Aggregation:detail" version="1.0">
            <property name="id" value="be86381c-4f10-44df-9f7e-d5bdb83225cb" valueType="string"/>
            <property name="name" value="NOMABREVIA" valueType="string"/>
            <property name="description" value="NOMBREABREVIA" valueType="string"/>
            <property name="overrideLookupInformation" value="false" valueType="boolean"/>
            <property name="displayFormat" value="" valueType="string"/>
            <property name="title" value="" valueType="string"/>
            <property name="overrideNullable" value="DEFAULT" valueType="string"/>
        </object>
        <object type="Aggregation:detail" version="1.0">
            <property name="id" value="2a44f0e1-cae9-4d31-9cfb-c5e55910f736" valueType="string"/>
            <property name="name" value="AX_ORNITDPFC" valueType="string"/>
            <property name="description" value="NIT sin DV" valueType="string"/>
            <property name="overrideLookupInformation" value="false" valueType="boolean"/>
            <property name="displayFormat" value="" valueType="string"/>
            <property name="title" value="" valueType="string"/>
            <property name="overrideNullable" value="DEFAULT" valueType="string"/>
        </object>
        <object type="Aggregation:detail" version="1.0">
            <property name="id" value="50a356b9-c217-4284-b8b4-14f5fb883bd0" valueType="string"/>
            <property name="name" value="CNCDTI" valueType="string"/>
            <property name="description" value="Tipo de Identificación" valueType="string"/>
            <property name="overrideLookupInformation" value="false" valueType="boolean"/>
            <property name="displayFormat" value="" valueType="string"/>
            <property name="title" value="" valueType="string"/>
            <property name="overrideNullable" value="DEFAULT" valueType="string"/>
        </object>
        <object type="Aggregation:detail" version="1.0">
            <property name="id" value="715e2fbd-3592-4a8e-9793-428333333904" valueType="string"/>
            <property name="name" value="CNNOSS" valueType="string"/>
            <property name="description" value="Núm. Identificación." valueType="string"/>
            <property name="overrideLookupInformation" value="false" valueType="boolean"/>
            <property name="displayFormat" value="" valueType="string"/>
            <property name="title" value="" valueType="string"/>
            <property name="overrideNullable" value="DEFAULT" valueType="string"/>
        </object>
        <object type="Aggregation:detail" version="1.0">
            <property name="id" value="e96e6de1-0871-48cc-8ee1-10335150ea9b" valueType="string"/>
            <property name="name" value="CNNAME" valueType="string"/>
            <property name="description" value="Nombre del Cliente" valueType="string"/>
            <property name="overrideLookupInformation" value="false" valueType="boolean"/>
            <property name="displayFormat" value="" valueType="string"/>
            <property name="title" value="" valueType="string"/>
            <property name="overrideNullable" value="DEFAULT" valueType="string"/>
        </object>
        <object type="Aggregation:detail" version="1.0">
            <property name="id" value="e4d831e1-90e7-42c0-922f-be5424c78050" valueType="string"/>
            <property name="name" value="CNCDBI" valueType="string"/>
            <property name="description" value="Segmento de Mercado" valueType="string"/>
            <property name="overrideLookupInformation" value="false" valueType="boolean"/>
            <property name="displayFormat" value="" valueType="string"/>
            <property name="title" value="" valueType="string"/>
            <property name="overrideNullable" value="DEFAULT" valueType="string"/>
        </object>
        <object type="Aggregation:detail" version="1.0">
            <property name="id" value="8da8602a-4b06-4a34-a077-fdbc36452c8a" valueType="string"/>
            <property name="name" value="CICDFM" valueType="string"/>
            <property name="description" value="Sexo" valueType="string"/>
            <property name="overrideLookupInformation" value="false" valueType="boolean"/>
            <property name="displayFormat" value="" valueType="string"/>
            <property name="title" value="" valueType="string"/>
            <property name="overrideNullable" value="DEFAULT" valueType="string"/>
        </object>
        <object type="Aggregation:detail" version="1.0">
            <property name="id" value="4a7a94a6-50e7-4a2b-ae52-bb172146d326" valueType="string"/>
            <property name="name" value="CNCDTY" valueType="string"/>
            <property name="description" value="Tipo de Cliente" valueType="string"/>
            <property name="overrideLookupInformation" value="false" valueType="boolean"/>
            <property name="displayFormat" value="" valueType="string"/>
            <property name="title" value="" valueType="string"/>
            <property name="overrideNullable" value="DEFAULT" valueType="string"/>
        </object>
        <object type="Aggregation:detail" version="1.0">
            <property name="id" value="87b750b1-89ef-41f4-80ae-6ec66d27da5f" valueType="string"/>
            <property name="name" value="CNCDVP" valueType="string"/>
            <property name="description" value="COdigo de Importancia" valueType="string"/>
            <property name="overrideLookupInformation" value="false" valueType="boolean"/>
            <property name="displayFormat" value="" valueType="string"/>
            <property name="title" value="" valueType="string"/>
            <property name="overrideNullable" value="DEFAULT" valueType="string"/>
        </object>
        <object type="Aggregation:detail" version="1.0">
            <property name="id" value="a5f7eda9-ded7-4826-aa18-c10f9d05c960" valueType="string"/>
            <property name="name" value="CNCDST" valueType="string"/>
            <property name="description" value="Estado" valueType="string"/>
            <property name="overrideLookupInformation" value="false" valueType="boolean"/>
            <property name="displayFormat" value="" valueType="string"/>
            <property name="title" value="" valueType="string"/>
            <property name="overrideNullable" value="DEFAULT" valueType="string"/>
        </object>
        <object type="Aggregation:detail" version="1.0">
            <property name="id" value="88fb2868-cf7c-4ff1-8c92-8bb67dc26f06" valueType="string"/>
            <property name="name" value="AX_CICDFM" valueType="string"/>
            <property name="description" value="AX_CICDFM" valueType="string"/>
            <property name="overrideLookupInformation" value="false" valueType="boolean"/>
            <property name="displayFormat" value="" valueType="string"/>
            <property name="title" value="" valueType="string"/>
            <property name="overrideNullable" value="DEFAULT" valueType="string"/>
        </object>
        <object type="Aggregation:detail" version="1.0">
            <property name="id" value="42fad49c-849f-4d74-a04c-9f73ccc3e46f" valueType="string"/>
            <property name="name" value="FUENTE" valueType="string"/>
            <property name="description" value="Fuente" valueType="string"/>
            <property name="overrideLookupInformation" value="false" valueType="boolean"/>
            <property name="displayFormat" value="" valueType="string"/>
            <property name="title" value="" valueType="string"/>
            <property name="overrideNullable" value="DEFAULT" valueType="string"/>
        </object>
        <object type="Aggregation:detail" version="1.0">
            <property name="id" value="3da7c318-de16-4eb6-b3bb-7afde7be51ad" valueType="string"/>
            <property name="name" value="PARAMETRO" valueType="string"/>
            <property name="description" value="Parametro" valueType="string"/>
            <property name="overrideLookupInformation" value="false" valueType="boolean"/>
            <property name="displayFormat" value="" valueType="string"/>
            <property name="title" value="" valueType="string"/>
            <property name="overrideNullable" value="DEFAULT" valueType="string"/>
        </object>
        <object type="Aggregation:detail" version="1.0">
            <property name="id" value="9f97ba7f-55dc-444e-a917-0b0d3bc6d414" valueType="string"/>
            <property name="name" value="CAMPO" valueType="string"/>
            <property name="description" value="Campo" valueType="string"/>
            <property name="overrideLookupInformation" value="false" valueType="boolean"/>
            <property name="displayFormat" value="" valueType="string"/>
            <property name="title" value="" valueType="string"/>
            <property name="overrideNullable" value="DEFAULT" valueType="string"/>
        </object>
        <object type="Aggregation:detail" version="1.0">
            <property name="id" value="635c1966-f643-4327-977e-5241953c175f" valueType="string"/>
            <property name="name" value="VALOR" valueType="string"/>
            <property name="description" value="Valor" valueType="string"/>
            <property name="overrideLookupInformation" value="false" valueType="boolean"/>
            <property name="displayFormat" value="" valueType="string"/>
            <property name="title" value="" valueType="string"/>
            <property name="overrideNullable" value="DEFAULT" valueType="string"/>
        </object>
        <object type="Aggregation:detail" version="1.0">
            <property name="id" value="db87f220-5eb1-42ba-a220-1aded3cc2fd8" valueType="string"/>
            <property name="name" value="VARIABLE" valueType="string"/>
            <property name="description" value="Variable" valueType="string"/>
            <property name="overrideLookupInformation" value="false" valueType="boolean"/>
            <property name="displayFormat" value="" valueType="string"/>
            <property name="title" value="" valueType="string"/>
            <property name="overrideNullable" value="DEFAULT" valueType="string"/>
        </object>
        <object type="Aggregation:detail" version="1.0">
            <property name="id" value="3443d53f-9c1a-4ecf-96ea-76130f793e1a" valueType="string"/>
            <property name="name" value="VALOR_MIN" valueType="string"/>
            <property name="description" value="Valor Minimo" valueType="string"/>
            <property name="overrideLookupInformation" value="false" valueType="boolean"/>
            <property name="displayFormat" value="" valueType="string"/>
            <property name="title" value="" valueType="string"/>
            <property name="overrideNullable" value="DEFAULT" valueType="string"/>
        </object>
        <object type="Aggregation:detail" version="1.0">
            <property name="id" value="b9e4dedb-fad7-40f8-84b8-c7bc984f8823" valueType="string"/>
            <property name="name" value="VALOR_MAX" valueType="string"/>
            <property name="description" value="Valor Maximo" valueType="string"/>
            <property name="overrideLookupInformation" value="false" valueType="boolean"/>
            <property name="displayFormat" value="" valueType="string"/>
            <property name="title" value="" valueType="string"/>
            <property name="overrideNullable" value="DEFAULT" valueType="string"/>
        </object>
        <object type="Aggregation:detail" version="1.0">
            <property name="id" value="7508d293-4003-4eb4-a3aa-332c40f8256f" valueType="string"/>
            <property name="name" value="DOCBCO" valueType="string"/>
            <property name="description" value="Obli_Homologada" valueType="string"/>
            <property name="overrideLookupInformation" value="false" valueType="boolean"/>
            <property name="displayFormat" value="" valueType="string"/>
            <property name="title" value="" valueType="string"/>
            <property name="overrideNullable" value="DEFAULT" valueType="string"/>
        </object>
        <object type="Aggregation:detail" version="1.0">
            <property name="id" value="9497e644-47b2-41bf-adc1-942d2876203c" valueType="string"/>
            <property name="name" value="SEGMENTO_PAG" valueType="string"/>
            <property name="description" value="Segmento pagador" valueType="string"/>
            <property name="overrideLookupInformation" value="false" valueType="boolean"/>
            <property name="displayFormat" value="" valueType="string"/>
            <property name="title" value="" valueType="string"/>
            <property name="overrideNullable" value="DEFAULT" valueType="string"/>
        </object>
        <object type="Aggregation:detail" version="1.0">
            <property name="id" value="cfc594fe-e0bc-45e3-99aa-9bcde4de2660" valueType="string"/>
            <property name="name" value="FECHAVENCE" valueType="string"/>
            <property name="description" value="Fecha de Vencimieno" valueType="string"/>
            <property name="overrideLookupInformation" value="false" valueType="boolean"/>
            <property name="displayFormat" value="" valueType="string"/>
            <property name="title" value="" valueType="string"/>
            <property name="overrideNullable" value="DEFAULT" valueType="string"/>
        </object>
    </property>
    <property name="calcFields" valueType="table">
        <object type="Aggregation:calcField" version="2.0">
            <property name="id" value="ea8adf66-bb25-4574-bf2b-71e3dd435465" valueType="string"/>
            <property name="name" value="GVALOR" valueType="string"/>
            <property name="description" value="Valor de la obligacion" valueType="string"/>
            <property name="aggrMethod" value="MAX" valueType="string"/>
            <property name="calcTotal" value="true" valueType="boolean"/>
            <property name="calcFormula" valueType="table"/>
            <property name="displayFormat" value="" valueType="string"/>
            <property name="overrideLookupInformation" value="false" valueType="boolean"/>
            <property name="title" value="" valueType="string"/>
            <property name="overrideNullable" value="DEFAULT" valueType="string"/>
        </object>
        <object type="Aggregation:calcField" version="2.0">
            <property name="id" value="babfb5e9-b5b6-4874-851e-e5a8636b1e76" valueType="string"/>
            <property name="name" value="TASAINTREM" valueType="string"/>
            <property name="description" value="Tasa de interes remuneratoria" valueType="string"/>
            <property name="aggrMethod" value="MAX" valueType="string"/>
            <property name="calcTotal" value="true" valueType="boolean"/>
            <property name="calcFormula" valueType="table"/>
            <property name="displayFormat" value="" valueType="string"/>
            <property name="overrideLookupInformation" value="false" valueType="boolean"/>
            <property name="title" value="" valueType="string"/>
            <property name="overrideNullable" value="DEFAULT" valueType="string"/>
        </object>
        <object type="Aggregation:calcField" version="2.0">
            <property name="id" value="73b01307-0934-40ed-8e8f-2abba35609f9" valueType="string"/>
            <property name="name" value="VALPAGCAPI" valueType="string"/>
            <property name="description" value="Valor pagado a capital" valueType="string"/>
            <property name="aggrMethod" value="MAX" valueType="string"/>
            <property name="calcTotal" value="true" valueType="boolean"/>
            <property name="calcFormula" valueType="table"/>
            <property name="displayFormat" value="" valueType="string"/>
            <property name="overrideLookupInformation" value="false" valueType="boolean"/>
            <property name="title" value="" valueType="string"/>
            <property name="overrideNullable" value="DEFAULT" valueType="string"/>
        </object>
        <object type="Aggregation:calcField" version="2.0">
            <property name="id" value="629e40c9-e5d7-4fbd-839b-4cd20067e386" valueType="string"/>
            <property name="name" value="GVALORN" valueType="string"/>
            <property name="description" value="Valor Neto de la Obligacion" valueType="string"/>
            <property name="aggrMethod" value="SUM" valueType="string"/>
            <property name="calcTotal" value="true" valueType="boolean"/>
            <property name="calcFormula" valueType="table"/>
            <property name="displayFormat" value="" valueType="string"/>
            <property name="overrideLookupInformation" value="false" valueType="boolean"/>
            <property name="title" value="" valueType="string"/>
            <property name="overrideNullable" value="DEFAULT" valueType="string"/>
        </object>
        <object type="Aggregation:calcField" version="2.0">
            <property name="id" value="3a5d3145-fd16-49ad-b049-d2fc45e8d3f1" valueType="string"/>
            <property name="name" value="VLRAMORTI" valueType="string"/>
            <property name="description" value="Valor amortizacion de la obligacion" valueType="string"/>
            <property name="aggrMethod" value="SUM" valueType="string"/>
            <property name="calcTotal" value="true" valueType="boolean"/>
            <property name="calcFormula" valueType="table"/>
            <property name="displayFormat" value="" valueType="string"/>
            <property name="overrideLookupInformation" value="false" valueType="boolean"/>
            <property name="title" value="" valueType="string"/>
            <property name="overrideNullable" value="DEFAULT" valueType="string"/>
        </object>
        <object type="Aggregation:calcField" version="2.0">
            <property name="id" value="b4c20227-0784-4065-ad5c-7d919dd1c483" valueType="string"/>
            <property name="name" value="PLAZO_DIA_PGADOR" valueType="string"/>
            <property name="description" value="PLAZO_DIA_PGADOR" valueType="string"/>
            <property name="aggrMethod" value="SUM" valueType="string"/>
            <property name="calcTotal" value="true" valueType="boolean"/>
            <property name="calcFormula" valueType="table"/>
            <property name="displayFormat" value="" valueType="string"/>
            <property name="overrideLookupInformation" value="false" valueType="boolean"/>
            <property name="title" value="" valueType="string"/>
            <property name="overrideNullable" value="DEFAULT" valueType="string"/>
        </object>
        <object type="Aggregation:calcField" version="2.0">
            <property name="id" value="7f48362b-ed64-4518-94c5-2f21ba67051e" valueType="string"/>
            <property name="name" value="TASA_EFECTIVA_CON_PAG" valueType="string"/>
            <property name="description" value="TASA_EFECTIVA_CON_RECURSO" valueType="string"/>
            <property name="aggrMethod" value="SUM" valueType="string"/>
            <property name="calcTotal" value="true" valueType="boolean"/>
            <property name="calcFormula" valueType="table"/>
            <property name="displayFormat" value="" valueType="string"/>
            <property name="overrideLookupInformation" value="false" valueType="boolean"/>
            <property name="title" value="" valueType="string"/>
            <property name="overrideNullable" value="DEFAULT" valueType="string"/>
        </object>
        <object type="Aggregation:calcField" version="2.0">
            <property name="id" value="9830b6f1-afe2-423f-bde4-d00e0c61b8aa" valueType="string"/>
            <property name="name" value="TASA_EFECTIVA_SIN_PAG" valueType="string"/>
            <property name="description" value="TASA_EFECTIVA_SIN_RECURSO" valueType="string"/>
            <property name="aggrMethod" value="SUM" valueType="string"/>
            <property name="calcTotal" value="true" valueType="boolean"/>
            <property name="calcFormula" valueType="table"/>
            <property name="displayFormat" value="" valueType="string"/>
            <property name="overrideLookupInformation" value="false" valueType="boolean"/>
            <property name="title" value="" valueType="string"/>
            <property name="overrideNullable" value="DEFAULT" valueType="string"/>
        </object>
    </property>
    <property name="auxFields" valueType="table"/>
    <property name="syntheticFields" valueType="table"/>
    <property name="additionalIndices" valueType="table"/>
    <property name="distributionStyle" valueType="object">
        <object type="Aggregation:distributionStyle" version="1.0">
            <property name="distStyle" value="INHERIT" valueType="string"/>
        </object>
    </property>
    <property name="mappings" valueType="table">
        <object type="Aggregation:mapping" version="2.0">
            <property name="field" valueType="object">
                <object type="Aggregation:localDetailReference" version="1.0">
                    <property name="value" valueType="url">Aggregation[this].details["GNIT"{baf2d342-0fac-4598-8e23-6416609117f0}]</property>
                </object>
            </property>
            <property name="fieldMapping" valueType="table">
                <object type="FieldMapping" version="2.0">
                    <property name="model" valueType="object">
                        <object type="DataModel:reference" version="1.0">
                            <property name="value" valueType="url">DataModel["F_414_FACTORING__PGD_TR"{25e8ebb7-3cad-4363-b464-d40e1e9f2a4c}]</property>
                        </object>
                    </property>
                    <property name="expression" valueType="table">
                        <object type="DataModel:fieldReference" version="1.0">
                            <property name="value" valueType="url">DataModel["F_414_FACTORING__PGD_TR"{25e8ebb7-3cad-4363-b464-d40e1e9f2a4c}].hierarchy["root"{f5507474-dc3c-484a-9fbd-c2278563d213}].dataSource.layout["GNIT"{00f0bb80-84ba-4190-855a-a8a9604d90bd}]</property>
                        </object>
                    </property>
                </object>
            </property>
        </object>
        <object type="Aggregation:mapping" version="2.0">
            <property name="field" valueType="object">
                <object type="Aggregation:localDetailReference" version="1.0">
                    <property name="value" valueType="url">Aggregation[this].details["GDOCTO"{6897bb33-73e3-46d2-a1b0-f3f124537da0}]</property>
                </object>
            </property>
            <property name="fieldMapping" valueType="table">
                <object type="FieldMapping" version="2.0">
                    <property name="model" valueType="object">
                        <object type="DataModel:reference" version="1.0">
                            <property name="value" valueType="url">DataModel["F_414_FACTORING__PGD_TR"{25e8ebb7-3cad-4363-b464-d40e1e9f2a4c}]</property>
                        </object>
                    </property>
                    <property name="expression" valueType="table">
                        <object type="DataModel:fieldReference" version="1.0">
                            <property name="value" valueType="url">DataModel["F_414_FACTORING__PGD_TR"{25e8ebb7-3cad-4363-b464-d40e1e9f2a4c}].hierarchy["root"{f5507474-dc3c-484a-9fbd-c2278563d213}].dataSource.layout["GDOCTO"{878d0dc1-b6bf-48ae-880d-322f90db938b}]</property>
                        </object>
                    </property>
                </object>
            </property>
        </object>
        <object type="Aggregation:mapping" version="2.0">
            <property name="field" valueType="object">
                <object type="Aggregation:localDetailReference" version="1.0">
                    <property name="value" valueType="url">Aggregation[this].details["VALUS"{8fad4486-fe7f-4d73-9361-5dc161fb347d}]</property>
                </object>
            </property>
            <property name="fieldMapping" valueType="table">
                <object type="FieldMapping" version="2.0">
                    <property name="model" valueType="object">
                        <object type="DataModel:reference" version="1.0">
                            <property name="value" valueType="url">DataModel["F_414_FACTORING__PGD_TR"{25e8ebb7-3cad-4363-b464-d40e1e9f2a4c}]</property>
                        </object>
                    </property>
                    <property name="expression" valueType="table">
                        <object type="DataModel:fieldReference" version="1.0">
                            <property name="value" valueType="url">DataModel["F_414_FACTORING__PGD_TR"{25e8ebb7-3cad-4363-b464-d40e1e9f2a4c}].hierarchy["root"{f5507474-dc3c-484a-9fbd-c2278563d213}].dataSource.layout["VALUS"{cac033fc-7e10-48c4-afc4-26c9ba26fa9d}]</property>
                        </object>
                    </property>
                </object>
            </property>
        </object>
        <object type="Aggregation:mapping" version="2.0">
            <property name="field" valueType="object">
                <object type="Aggregation:localDetailReference" version="1.0">
                    <property name="value" valueType="url">Aggregation[this].details["GLINEA"{3d7dcea0-6d43-4901-b8be-b8a01af2da7b}]</property>
                </object>
            </property>
            <property name="fieldMapping" valueType="table">
                <object type="FieldMapping" version="2.0">
                    <property name="model" valueType="object">
                        <object type="DataModel:reference" version="1.0">
                            <property name="value" valueType="url">DataModel["F_414_FACTORING__PGD_TR"{25e8ebb7-3cad-4363-b464-d40e1e9f2a4c}]</property>
                        </object>
                    </property>
                    <property name="expression" valueType="table">
                        <object type="DataModel:fieldReference" version="1.0">
                            <property name="value" valueType="url">DataModel["F_414_FACTORING__PGD_TR"{25e8ebb7-3cad-4363-b464-d40e1e9f2a4c}].hierarchy["root"{f5507474-dc3c-484a-9fbd-c2278563d213}].dataSource.layout["GLINEA"{fe063471-4b23-4c1d-bdf8-bcfcd4c1d5e1}]</property>
                        </object>
                    </property>
                </object>
            </property>
        </object>
        <object type="Aggregation:mapping" version="2.0">
            <property name="field" valueType="object">
                <object type="Aggregation:localDetailReference" version="1.0">
                    <property name="value" valueType="url">Aggregation[this].details["TIPOCREDI"{e38617c1-6b65-4319-8886-bc668ef0d7a8}]</property>
                </object>
            </property>
            <property name="fieldMapping" valueType="table">
                <object type="FieldMapping" version="2.0">
                    <property name="model" valueType="object">
                        <object type="DataModel:reference" version="1.0">
                            <property name="value" valueType="url">DataModel["F_414_FACTORING__PGD_TR"{25e8ebb7-3cad-4363-b464-d40e1e9f2a4c}]</property>
                        </object>
                    </property>
                    <property name="expression" valueType="table">
                        <object type="DataModel:fieldReference" version="1.0">
                            <property name="value" valueType="url">DataModel["F_414_FACTORING__PGD_TR"{25e8ebb7-3cad-4363-b464-d40e1e9f2a4c}].hierarchy["root"{f5507474-dc3c-484a-9fbd-c2278563d213}].dataSource.layout["TIPOCREDI"{d14b9b31-f884-4b2c-a326-8a26d7d0c0a9}]</property>
                        </object>
                    </property>
                </object>
            </property>
        </object>
        <object type="Aggregation:mapping" version="2.0">
            <property name="field" valueType="object">
                <object type="Aggregation:localDetailReference" version="1.0">
                    <property name="value" valueType="url">Aggregation[this].details["DIANETOR"{a44a5c1e-2c4c-4d47-8a69-8192f1b1f95a}]</property>
                </object>
            </property>
            <property name="fieldMapping" valueType="table">
                <object type="FieldMapping" version="2.0">
                    <property name="model" valueType="object">
                        <object type="DataModel:reference" version="1.0">
                            <property name="value" valueType="url">DataModel["F_414_FACTORING__PGD_TR"{25e8ebb7-3cad-4363-b464-d40e1e9f2a4c}]</property>
                        </object>
                    </property>
                    <property name="expression" valueType="table">
                        <object type="DataModel:fieldReference" version="1.0">
                            <property name="value" valueType="url">DataModel["F_414_FACTORING__PGD_TR"{25e8ebb7-3cad-4363-b464-d40e1e9f2a4c}].hierarchy["root"{f5507474-dc3c-484a-9fbd-c2278563d213}].dataSource.layout["DIANETOR"{e0588cae-198a-4ba7-b52d-6cc44b016824}]</property>
                        </object>
                    </property>
                </object>
            </property>
        </object>
        <object type="Aggregation:mapping" version="2.0">
            <property name="field" valueType="object">
                <object type="Aggregation:localDetailReference" version="1.0">
                    <property name="value" valueType="url">Aggregation[this].details["TIPOTASA"{fc894e54-eb9b-4178-977f-2aee2d69c59b}]</property>
                </object>
            </property>
            <property name="fieldMapping" valueType="table">
                <object type="FieldMapping" version="2.0">
                    <property name="model" valueType="object">
                        <object type="DataModel:reference" version="1.0">
                            <property name="value" valueType="url">DataModel["F_414_FACTORING__PGD_TR"{25e8ebb7-3cad-4363-b464-d40e1e9f2a4c}]</property>
                        </object>
                    </property>
                    <property name="expression" valueType="table">
                        <object type="DataModel:fieldReference" version="1.0">
                            <property name="value" valueType="url">DataModel["F_414_FACTORING__PGD_TR"{25e8ebb7-3cad-4363-b464-d40e1e9f2a4c}].hierarchy["root"{f5507474-dc3c-484a-9fbd-c2278563d213}].dataSource.layout["TIPOTASA"{8f0e1e71-86c2-4952-8ce2-db4c29275a73}]</property>
                        </object>
                    </property>
                </object>
            </property>
        </object>
        <object type="Aggregation:mapping" version="2.0">
            <property name="field" valueType="object">
                <object type="Aggregation:localDetailReference" version="1.0">
                    <property name="value" valueType="url">Aggregation[this].details["FECHACONTA"{b82c2db2-3785-4cc9-abe6-34c9e5e2f414}]</property>
                </object>
            </property>
            <property name="fieldMapping" valueType="table">
                <object type="FieldMapping" version="2.0">
                    <property name="model" valueType="object">
                        <object type="DataModel:reference" version="1.0">
                            <property name="value" valueType="url">DataModel["F_414_FACTORING__PGD_TR"{25e8ebb7-3cad-4363-b464-d40e1e9f2a4c}]</property>
                        </object>
                    </property>
                    <property name="expression" valueType="table">
                        <object type="DataModel:fieldReference" version="1.0">
                            <property name="value" valueType="url">DataModel["F_414_FACTORING__PGD_TR"{25e8ebb7-3cad-4363-b464-d40e1e9f2a4c}].hierarchy["root"{f5507474-dc3c-484a-9fbd-c2278563d213}].dataSource.layout["FECHACONTA"{cc239f4b-32dd-475d-80a9-0e7016d378d1}]</property>
                        </object>
                    </property>
                </object>
            </property>
        </object>
        <object type="Aggregation:mapping" version="2.0">
            <property name="field" valueType="object">
                <object type="Aggregation:localDetailReference" version="1.0">
                    <property name="value" valueType="url">Aggregation[this].details["ESTADOBLIG"{0bf6af55-e5bb-4375-8eb2-0efbb170b741}]</property>
                </object>
            </property>
            <property name="fieldMapping" valueType="table">
                <object type="FieldMapping" version="2.0">
                    <property name="model" valueType="object">
                        <object type="DataModel:reference" version="1.0">
                            <property name="value" valueType="url">DataModel["F_414_FACTORING__PGD_TR"{25e8ebb7-3cad-4363-b464-d40e1e9f2a4c}]</property>
                        </object>
                    </property>
                    <property name="expression" valueType="table">
                        <object type="DataModel:fieldReference" version="1.0">
                            <property name="value" valueType="url">DataModel["F_414_FACTORING__PGD_TR"{25e8ebb7-3cad-4363-b464-d40e1e9f2a4c}].hierarchy["root"{f5507474-dc3c-484a-9fbd-c2278563d213}].dataSource.layout["ESTADOBLIG"{61c05660-6c2b-4a48-a74b-12def716788c}]</property>
                        </object>
                    </property>
                </object>
            </property>
        </object>
        <object type="Aggregation:mapping" version="2.0">
            <property name="field" valueType="object">
                <object type="Aggregation:localDetailReference" version="1.0">
                    <property name="value" valueType="url">Aggregation[this].details["GPLAN"{c290354b-6ad6-498b-a53e-208b54c24925}]</property>
                </object>
            </property>
            <property name="fieldMapping" valueType="table">
                <object type="FieldMapping" version="2.0">
                    <property name="model" valueType="object">
                        <object type="DataModel:reference" version="1.0">
                            <property name="value" valueType="url">DataModel["F_414_FACTORING__PGD_TR"{25e8ebb7-3cad-4363-b464-d40e1e9f2a4c}]</property>
                        </object>
                    </property>
                    <property name="expression" valueType="table">
                        <object type="DataModel:fieldReference" version="1.0">
                            <property name="value" valueType="url">DataModel["F_414_FACTORING__PGD_TR"{25e8ebb7-3cad-4363-b464-d40e1e9f2a4c}].hierarchy["root"{f5507474-dc3c-484a-9fbd-c2278563d213}].dataSource.layout["GPLAN"{efb14221-49fa-47c4-a4b0-a3f50505eecc}]</property>
                        </object>
                    </property>
                </object>
            </property>
        </object>
        <object type="Aggregation:mapping" version="2.0">
            <property name="field" valueType="object">
                <object type="Aggregation:localDetailReference" version="1.0">
                    <property name="value" valueType="url">Aggregation[this].details["FECHAVENCE_COL"{7ab4b2f3-5260-49dc-a2e5-fb839b5bfcf8}]</property>
                </object>
            </property>
            <property name="fieldMapping" valueType="table">
                <object type="FieldMapping" version="2.0">
                    <property name="model" valueType="object">
                        <object type="DataModel:reference" version="1.0">
                            <property name="value" valueType="url">DataModel["F_414_FACTORING__PGD_TR"{25e8ebb7-3cad-4363-b464-d40e1e9f2a4c}]</property>
                        </object>
                    </property>
                    <property name="expression" valueType="table">
                        <object type="DataModel:fieldReference" version="1.0">
                            <property name="value" valueType="url">DataModel["F_414_FACTORING__PGD_TR"{25e8ebb7-3cad-4363-b464-d40e1e9f2a4c}].hierarchy["root"{f5507474-dc3c-484a-9fbd-c2278563d213}].dataSource.layout["FECHAVENCE_MCCOL"{d8761350-5367-42c6-b3b3-c70c89c84602}]</property>
                        </object>
                    </property>
                </object>
            </property>
        </object>
        <object type="Aggregation:mapping" version="2.0">
            <property name="field" valueType="object">
                <object type="Aggregation:localDetailReference" version="1.0">
                    <property name="value" valueType="url">Aggregation[this].details["FECHAPLICA"{f46c077a-f972-4dd9-b938-65f90b5fa2e4}]</property>
                </object>
            </property>
            <property name="fieldMapping" valueType="table">
                <object type="FieldMapping" version="2.0">
                    <property name="model" valueType="object">
                        <object type="DataModel:reference" version="1.0">
                            <property name="value" valueType="url">DataModel["F_414_FACTORING__PGD_TR"{25e8ebb7-3cad-4363-b464-d40e1e9f2a4c}]</property>
                        </object>
                    </property>
                    <property name="expression" valueType="table">
                        <object type="DataModel:fieldReference" version="1.0">
                            <property name="value" valueType="url">DataModel["F_414_FACTORING__PGD_TR"{25e8ebb7-3cad-4363-b464-d40e1e9f2a4c}].hierarchy["root"{f5507474-dc3c-484a-9fbd-c2278563d213}].dataSource.layout["FECHAPLICA"{1852d450-c0df-4f08-b61e-a5026101f2ed}]</property>
                        </object>
                    </property>
                </object>
            </property>
        </object>
        <object type="Aggregation:mapping" version="2.0">
            <property name="field" valueType="object">
                <object type="Aggregation:localDetailReference" version="1.0">
                    <property name="value" valueType="url">Aggregation[this].details["GNIT_NODV"{d5423c53-9166-4425-a0fc-4d99201403c5}]</property>
                </object>
            </property>
            <property name="fieldMapping" valueType="table">
                <object type="FieldMapping" version="2.0">
                    <property name="model" valueType="object">
                        <object type="DataModel:reference" version="1.0">
                            <property name="value" valueType="url">DataModel["F_414_FACTORING__PGD_TR"{25e8ebb7-3cad-4363-b464-d40e1e9f2a4c}]</property>
                        </object>
                    </property>
                    <property name="expression" valueType="table">
                        <object type="DataModel:fieldReference" version="1.0">
                            <property name="value" valueType="url">DataModel["F_414_FACTORING__PGD_TR"{25e8ebb7-3cad-4363-b464-d40e1e9f2a4c}].hierarchy["root"{f5507474-dc3c-484a-9fbd-c2278563d213}].dataSource.layout["GNIT_NODV"{3f2b62ec-6577-4856-b0e1-7a43747e5ed4}]</property>
                        </object>
                    </property>
                </object>
            </property>
        </object>
        <object type="Aggregation:mapping" version="2.0">
            <property name="field" valueType="object">
                <object type="Aggregation:localDetailReference" version="1.0">
                    <property name="value" valueType="url">Aggregation[this].details["TIPIDEN"{364fec5b-b62c-477e-8436-ca0f0d6b71f7}]</property>
                </object>
            </property>
            <property name="fieldMapping" valueType="table">
                <object type="FieldMapping" version="2.0">
                    <property name="model" valueType="object">
                        <object type="DataModel:reference" version="1.0">
                            <property name="value" valueType="url">DataModel["F_414_FACTORING__PGD_TR"{25e8ebb7-3cad-4363-b464-d40e1e9f2a4c}]</property>
                        </object>
                    </property>
                    <property name="expression" valueType="table">
                        <object type="DataModel:fieldReference" version="1.0">
                            <property name="value" valueType="url">DataModel["F_414_FACTORING__PGD_TR"{25e8ebb7-3cad-4363-b464-d40e1e9f2a4c}].hierarchy["root"{f5507474-dc3c-484a-9fbd-c2278563d213}].dataSource.layout["TIPIDEN"{b2a13652-2625-47b6-84a5-ac9e95183da4}]</property>
                        </object>
                    </property>
                </object>
            </property>
        </object>
        <object type="Aggregation:mapping" version="2.0">
            <property name="field" valueType="object">
                <object type="Aggregation:localDetailReference" version="1.0">
                    <property name="value" valueType="url">Aggregation[this].details["CALIF"{2c547571-7fc4-4c0f-b9e8-f5b32264e05d}]</property>
                </object>
            </property>
            <property name="fieldMapping" valueType="table">
                <object type="FieldMapping" version="2.0">
                    <property name="model" valueType="object">
                        <object type="DataModel:reference" version="1.0">
                            <property name="value" valueType="url">DataModel["F_414_FACTORING__PGD_TR"{25e8ebb7-3cad-4363-b464-d40e1e9f2a4c}]</property>
                        </object>
                    </property>
                    <property name="expression" valueType="table">
                        <object type="DataModel:fieldReference" version="1.0">
                            <property name="value" valueType="url">DataModel["F_414_FACTORING__PGD_TR"{25e8ebb7-3cad-4363-b464-d40e1e9f2a4c}].hierarchy["root"{f5507474-dc3c-484a-9fbd-c2278563d213}].dataSource.layout["CALIF"{320f5f48-976a-47b4-b76b-99fab7c89aae}]</property>
                        </object>
                    </property>
                </object>
            </property>
        </object>
        <object type="Aggregation:mapping" version="2.0">
            <property name="field" valueType="object">
                <object type="Aggregation:localDetailReference" version="1.0">
                    <property name="value" valueType="url">Aggregation[this].details["NOMABREVIA"{be86381c-4f10-44df-9f7e-d5bdb83225cb}]</property>
                </object>
            </property>
            <property name="fieldMapping" valueType="table">
                <object type="FieldMapping" version="2.0">
                    <property name="model" valueType="object">
                        <object type="DataModel:reference" version="1.0">
                            <property name="value" valueType="url">DataModel["F_414_FACTORING__PGD_TR"{25e8ebb7-3cad-4363-b464-d40e1e9f2a4c}]</property>
                        </object>
                    </property>
                    <property name="expression" valueType="table">
                        <object type="DataModel:fieldReference" version="1.0">
                            <property name="value" valueType="url">DataModel["F_414_FACTORING__PGD_TR"{25e8ebb7-3cad-4363-b464-d40e1e9f2a4c}].hierarchy["root"{f5507474-dc3c-484a-9fbd-c2278563d213}].dataSource.layout["NOMABREVIA"{215a65ed-4b1e-42a4-9733-7751499921e9}]</property>
                        </object>
                    </property>
                </object>
            </property>
        </object>
        <object type="Aggregation:mapping" version="2.0">
            <property name="field" valueType="object">
                <object type="Aggregation:localDetailReference" version="1.0">
                    <property name="value" valueType="url">Aggregation[this].details["AX_ORNITDPFC"{2a44f0e1-cae9-4d31-9cfb-c5e55910f736}]</property>
                </object>
            </property>
            <property name="fieldMapping" valueType="table">
                <object type="FieldMapping" version="2.0">
                    <property name="model" valueType="object">
                        <object type="DataModel:reference" version="1.0">
                            <property name="value" valueType="url">DataModel["F_414_FACTORING__PGD_TR"{25e8ebb7-3cad-4363-b464-d40e1e9f2a4c}]</property>
                        </object>
                    </property>
                    <property name="expression" valueType="table">
                        <object type="DataModel:fieldReference" version="1.0">
                            <property name="value" valueType="url">DataModel["F_414_FACTORING__PGD_TR"{25e8ebb7-3cad-4363-b464-d40e1e9f2a4c}].hierarchy["root"{f5507474-dc3c-484a-9fbd-c2278563d213}].dataSource.layout["AX_ORNITDPFC"{6e0e0fb6-6b20-4d77-9cd9-e338335d2490}]</property>
                        </object>
                    </property>
                </object>
            </property>
        </object>
        <object type="Aggregation:mapping" version="2.0">
            <property name="field" valueType="object">
                <object type="Aggregation:localDetailReference" version="1.0">
                    <property name="value" valueType="url">Aggregation[this].details["CNCDTI"{50a356b9-c217-4284-b8b4-14f5fb883bd0}]</property>
                </object>
            </property>
            <property name="fieldMapping" valueType="table">
                <object type="FieldMapping" version="2.0">
                    <property name="model" valueType="object">
                        <object type="DataModel:reference" version="1.0">
                            <property name="value" valueType="url">DataModel["F_414_FACTORING__PGD_TR"{25e8ebb7-3cad-4363-b464-d40e1e9f2a4c}]</property>
                        </object>
                    </property>
                    <property name="expression" valueType="table">
                        <object type="DataModel:fieldReference" version="1.0">
                            <property name="value" valueType="url">DataModel["F_414_FACTORING__PGD_TR"{25e8ebb7-3cad-4363-b464-d40e1e9f2a4c}].hierarchy["root"{f5507474-dc3c-484a-9fbd-c2278563d213}].dataSource.layout["CNCDTI"{9b42ef6e-7f89-499c-81f4-6532a5aa75c0}]</property>
                        </object>
                    </property>
                </object>
            </property>
        </object>
        <object type="Aggregation:mapping" version="2.0">
            <property name="field" valueType="object">
                <object type="Aggregation:localDetailReference" version="1.0">
                    <property name="value" valueType="url">Aggregation[this].details["CNNOSS"{715e2fbd-3592-4a8e-9793-428333333904}]</property>
                </object>
            </property>
            <property name="fieldMapping" valueType="table">
                <object type="FieldMapping" version="2.0">
                    <property name="model" valueType="object">
                        <object type="DataModel:reference" version="1.0">
                            <property name="value" valueType="url">DataModel["F_414_FACTORING__PGD_TR"{25e8ebb7-3cad-4363-b464-d40e1e9f2a4c}]</property>
                        </object>
                    </property>
                    <property name="expression" valueType="table">
                        <object type="DataModel:fieldReference" version="1.0">
                            <property name="value" valueType="url">DataModel["F_414_FACTORING__PGD_TR"{25e8ebb7-3cad-4363-b464-d40e1e9f2a4c}].hierarchy["root"{f5507474-dc3c-484a-9fbd-c2278563d213}].dataSource.layout["CNNOSS"{48c2abd8-5ea4-4af7-ae7c-33252b2edcae}]</property>
                        </object>
                    </property>
                </object>
            </property>
        </object>
        <object type="Aggregation:mapping" version="2.0">
            <property name="field" valueType="object">
                <object type="Aggregation:localDetailReference" version="1.0">
                    <property name="value" valueType="url">Aggregation[this].details["CNNAME"{e96e6de1-0871-48cc-8ee1-10335150ea9b}]</property>
                </object>
            </property>
            <property name="fieldMapping" valueType="table">
                <object type="FieldMapping" version="2.0">
                    <property name="model" valueType="object">
                        <object type="DataModel:reference" version="1.0">
                            <property name="value" valueType="url">DataModel["F_414_FACTORING__PGD_TR"{25e8ebb7-3cad-4363-b464-d40e1e9f2a4c}]</property>
                        </object>
                    </property>
                    <property name="expression" valueType="table">
                        <object type="DataModel:fieldReference" version="1.0">
                            <property name="value" valueType="url">DataModel["F_414_FACTORING__PGD_TR"{25e8ebb7-3cad-4363-b464-d40e1e9f2a4c}].hierarchy["root"{f5507474-dc3c-484a-9fbd-c2278563d213}].dataSource.layout["CNNAME"{57792861-c543-4ed7-b4f6-2220c615d081}]</property>
                        </object>
                    </property>
                </object>
            </property>
        </object>
        <object type="Aggregation:mapping" version="2.0">
            <property name="field" valueType="object">
                <object type="Aggregation:localDetailReference" version="1.0">
                    <property name="value" valueType="url">Aggregation[this].details["CNCDBI"{e4d831e1-90e7-42c0-922f-be5424c78050}]</property>
                </object>
            </property>
            <property name="fieldMapping" valueType="table">
                <object type="FieldMapping" version="2.0">
                    <property name="model" valueType="object">
                        <object type="DataModel:reference" version="1.0">
                            <property name="value" valueType="url">DataModel["F_414_FACTORING__PGD_TR"{25e8ebb7-3cad-4363-b464-d40e1e9f2a4c}]</property>
                        </object>
                    </property>
                    <property name="expression" valueType="table">
                        <object type="DataModel:fieldReference" version="1.0">
                            <property name="value" valueType="url">DataModel["F_414_FACTORING__PGD_TR"{25e8ebb7-3cad-4363-b464-d40e1e9f2a4c}].hierarchy["root"{f5507474-dc3c-484a-9fbd-c2278563d213}].dataSource.layout["CNCDBI"{8e1db584-459f-44c9-b140-feb05455f1b3}]</property>
                        </object>
                    </property>
                </object>
            </property>
        </object>
        <object type="Aggregation:mapping" version="2.0">
            <property name="field" valueType="object">
                <object type="Aggregation:localDetailReference" version="1.0">
                    <property name="value" valueType="url">Aggregation[this].details["CICDFM"{8da8602a-4b06-4a34-a077-fdbc36452c8a}]</property>
                </object>
            </property>
            <property name="fieldMapping" valueType="table">
                <object type="FieldMapping" version="2.0">
                    <property name="model" valueType="object">
                        <object type="DataModel:reference" version="1.0">
                            <property name="value" valueType="url">DataModel["F_414_FACTORING__PGD_TR"{25e8ebb7-3cad-4363-b464-d40e1e9f2a4c}]</property>
                        </object>
                    </property>
                    <property name="expression" valueType="table">
                        <object type="DataModel:fieldReference" version="1.0">
                            <property name="value" valueType="url">DataModel["F_414_FACTORING__PGD_TR"{25e8ebb7-3cad-4363-b464-d40e1e9f2a4c}].hierarchy["root"{f5507474-dc3c-484a-9fbd-c2278563d213}].dataSource.layout["CICDFM"{c6c62818-30bc-4b16-a1d3-ddd80b7b6449}]</property>
                        </object>
                    </property>
                </object>
            </property>
        </object>
        <object type="Aggregation:mapping" version="2.0">
            <property name="field" valueType="object">
                <object type="Aggregation:localDetailReference" version="1.0">
                    <property name="value" valueType="url">Aggregation[this].details["CNCDTY"{4a7a94a6-50e7-4a2b-ae52-bb172146d326}]</property>
                </object>
            </property>
            <property name="fieldMapping" valueType="table">
                <object type="FieldMapping" version="2.0">
                    <property name="model" valueType="object">
                        <object type="DataModel:reference" version="1.0">
                            <property name="value" valueType="url">DataModel["F_414_FACTORING__PGD_TR"{25e8ebb7-3cad-4363-b464-d40e1e9f2a4c}]</property>
                        </object>
                    </property>
                    <property name="expression" valueType="table">
                        <object type="DataModel:fieldReference" version="1.0">
                            <property name="value" valueType="url">DataModel["F_414_FACTORING__PGD_TR"{25e8ebb7-3cad-4363-b464-d40e1e9f2a4c}].hierarchy["root"{f5507474-dc3c-484a-9fbd-c2278563d213}].dataSource.layout["CNCDTY"{5be1b863-cbac-4d5a-90be-41debed059b7}]</property>
                        </object>
                    </property>
                </object>
            </property>
        </object>
        <object type="Aggregation:mapping" version="2.0">
            <property name="field" valueType="object">
                <object type="Aggregation:localDetailReference" version="1.0">
                    <property name="value" valueType="url">Aggregation[this].details["CNCDVP"{87b750b1-89ef-41f4-80ae-6ec66d27da5f}]</property>
                </object>
            </property>
            <property name="fieldMapping" valueType="table">
                <object type="FieldMapping" version="2.0">
                    <property name="model" valueType="object">
                        <object type="DataModel:reference" version="1.0">
                            <property name="value" valueType="url">DataModel["F_414_FACTORING__PGD_TR"{25e8ebb7-3cad-4363-b464-d40e1e9f2a4c}]</property>
                        </object>
                    </property>
                    <property name="expression" valueType="table">
                        <object type="DataModel:fieldReference" version="1.0">
                            <property name="value" valueType="url">DataModel["F_414_FACTORING__PGD_TR"{25e8ebb7-3cad-4363-b464-d40e1e9f2a4c}].hierarchy["root"{f5507474-dc3c-484a-9fbd-c2278563d213}].dataSource.layout["CNCDVP"{bcff21e6-22ea-4818-bee4-aeef8f966bea}]</property>
                        </object>
                    </property>
                </object>
            </property>
        </object>
        <object type="Aggregation:mapping" version="2.0">
            <property name="field" valueType="object">
                <object type="Aggregation:localDetailReference" version="1.0">
                    <property name="value" valueType="url">Aggregation[this].details["CNCDST"{a5f7eda9-ded7-4826-aa18-c10f9d05c960}]</property>
                </object>
            </property>
            <property name="fieldMapping" valueType="table">
                <object type="FieldMapping" version="2.0">
                    <property name="model" valueType="object">
                        <object type="DataModel:reference" version="1.0">
                            <property name="value" valueType="url">DataModel["F_414_FACTORING__PGD_TR"{25e8ebb7-3cad-4363-b464-d40e1e9f2a4c}]</property>
                        </object>
                    </property>
                    <property name="expression" valueType="table">
                        <object type="DataModel:fieldReference" version="1.0">
                            <property name="value" valueType="url">DataModel["F_414_FACTORING__PGD_TR"{25e8ebb7-3cad-4363-b464-d40e1e9f2a4c}].hierarchy["root"{f5507474-dc3c-484a-9fbd-c2278563d213}].dataSource.layout["CNCDST"{da5cc489-1243-4de9-bb90-bc02f422338c}]</property>
                        </object>
                    </property>
                </object>
            </property>
        </object>
        <object type="Aggregation:mapping" version="2.0">
            <property name="field" valueType="object">
                <object type="Aggregation:localDetailReference" version="1.0">
                    <property name="value" valueType="url">Aggregation[this].details["AX_CICDFM"{88fb2868-cf7c-4ff1-8c92-8bb67dc26f06}]</property>
                </object>
            </property>
            <property name="fieldMapping" valueType="table">
                <object type="FieldMapping" version="2.0">
                    <property name="model" valueType="object">
                        <object type="DataModel:reference" version="1.0">
                            <property name="value" valueType="url">DataModel["F_414_FACTORING__PGD_TR"{25e8ebb7-3cad-4363-b464-d40e1e9f2a4c}]</property>
                        </object>
                    </property>
                    <property name="expression" valueType="table">
                        <object type="DataModel:fieldReference" version="1.0">
                            <property name="value" valueType="url">DataModel["F_414_FACTORING__PGD_TR"{25e8ebb7-3cad-4363-b464-d40e1e9f2a4c}].hierarchy["root"{f5507474-dc3c-484a-9fbd-c2278563d213}].dataSource.layout["AX_CICDFM"{0a1a7838-f1c9-4e7b-b346-cc770ca8a91e}]</property>
                        </object>
                    </property>
                </object>
            </property>
        </object>
        <object type="Aggregation:mapping" version="2.0">
            <property name="field" valueType="object">
                <object type="Aggregation:localDetailReference" version="1.0">
                    <property name="value" valueType="url">Aggregation[this].details["FUENTE"{42fad49c-849f-4d74-a04c-9f73ccc3e46f}]</property>
                </object>
            </property>
            <property name="fieldMapping" valueType="table">
                <object type="FieldMapping" version="2.0">
                    <property name="model" valueType="object">
                        <object type="DataModel:reference" version="1.0">
                            <property name="value" valueType="url">DataModel["F_414_FACTORING__PGD_TR"{25e8ebb7-3cad-4363-b464-d40e1e9f2a4c}]</property>
                        </object>
                    </property>
                    <property name="expression" valueType="table">
                        <object type="DataModel:fieldReference" version="1.0">
                            <property name="value" valueType="url">DataModel["F_414_FACTORING__PGD_TR"{25e8ebb7-3cad-4363-b464-d40e1e9f2a4c}].hierarchy["TR_PARAMETROS_F414"{ae9d3ed1-dbe9-48a0-9806-aa645d8b124f}].dataSource.layout["FUENTE"{d80c5604-565a-4b84-b1ee-d18d791e411f}]</property>
                        </object>
                    </property>
                </object>
            </property>
        </object>
        <object type="Aggregation:mapping" version="2.0">
            <property name="field" valueType="object">
                <object type="Aggregation:localDetailReference" version="1.0">
                    <property name="value" valueType="url">Aggregation[this].details["PARAMETRO"{3da7c318-de16-4eb6-b3bb-7afde7be51ad}]</property>
                </object>
            </property>
            <property name="fieldMapping" valueType="table">
                <object type="FieldMapping" version="2.0">
                    <property name="model" valueType="object">
                        <object type="DataModel:reference" version="1.0">
                            <property name="value" valueType="url">DataModel["F_414_FACTORING__PGD_TR"{25e8ebb7-3cad-4363-b464-d40e1e9f2a4c}]</property>
                        </object>
                    </property>
                    <property name="expression" valueType="table">
                        <object type="DataModel:fieldReference" version="1.0">
                            <property name="value" valueType="url">DataModel["F_414_FACTORING__PGD_TR"{25e8ebb7-3cad-4363-b464-d40e1e9f2a4c}].hierarchy["TR_PARAMETROS_F414"{ae9d3ed1-dbe9-48a0-9806-aa645d8b124f}].dataSource.layout["PARAMETRO"{76ba8205-c9f9-4d8a-afc1-c61bd66f8775}]</property>
                        </object>
                    </property>
                </object>
            </property>
        </object>
        <object type="Aggregation:mapping" version="2.0">
            <property name="field" valueType="object">
                <object type="Aggregation:localDetailReference" version="1.0">
                    <property name="value" valueType="url">Aggregation[this].details["CAMPO"{9f97ba7f-55dc-444e-a917-0b0d3bc6d414}]</property>
                </object>
            </property>
            <property name="fieldMapping" valueType="table">
                <object type="FieldMapping" version="2.0">
                    <property name="model" valueType="object">
                        <object type="DataModel:reference" version="1.0">
                            <property name="value" valueType="url">DataModel["F_414_FACTORING__PGD_TR"{25e8ebb7-3cad-4363-b464-d40e1e9f2a4c}]</property>
                        </object>
                    </property>
                    <property name="expression" valueType="table">
                        <object type="DataModel:fieldReference" version="1.0">
                            <property name="value" valueType="url">DataModel["F_414_FACTORING__PGD_TR"{25e8ebb7-3cad-4363-b464-d40e1e9f2a4c}].hierarchy["TR_PARAMETROS_F414"{ae9d3ed1-dbe9-48a0-9806-aa645d8b124f}].dataSource.layout["CAMPO"{01e1bc3c-90ba-4b9d-aa0c-d109bfbf2ee6}]</property>
                        </object>
                    </property>
                </object>
            </property>
        </object>
        <object type="Aggregation:mapping" version="2.0">
            <property name="field" valueType="object">
                <object type="Aggregation:localDetailReference" version="1.0">
                    <property name="value" valueType="url">Aggregation[this].details["VALOR"{635c1966-f643-4327-977e-5241953c175f}]</property>
                </object>
            </property>
            <property name="fieldMapping" valueType="table">
                <object type="FieldMapping" version="2.0">
                    <property name="model" valueType="object">
                        <object type="DataModel:reference" version="1.0">
                            <property name="value" valueType="url">DataModel["F_414_FACTORING__PGD_TR"{25e8ebb7-3cad-4363-b464-d40e1e9f2a4c}]</property>
                        </object>
                    </property>
                    <property name="expression" valueType="table">
                        <object type="DataModel:fieldReference" version="1.0">
                            <property name="value" valueType="url">DataModel["F_414_FACTORING__PGD_TR"{25e8ebb7-3cad-4363-b464-d40e1e9f2a4c}].hierarchy["TR_PARAMETROS_F414"{ae9d3ed1-dbe9-48a0-9806-aa645d8b124f}].dataSource.layout["VALOR"{25fe2ff2-f416-496a-a441-330fddacc070}]</property>
                        </object>
                    </property>
                </object>
            </property>
        </object>
        <object type="Aggregation:mapping" version="2.0">
            <property name="field" valueType="object">
                <object type="Aggregation:localDetailReference" version="1.0">
                    <property name="value" valueType="url">Aggregation[this].details["VARIABLE"{db87f220-5eb1-42ba-a220-1aded3cc2fd8}]</property>
                </object>
            </property>
            <property name="fieldMapping" valueType="table">
                <object type="FieldMapping" version="2.0">
                    <property name="model" valueType="object">
                        <object type="DataModel:reference" version="1.0">
                            <property name="value" valueType="url">DataModel["F_414_FACTORING__PGD_TR"{25e8ebb7-3cad-4363-b464-d40e1e9f2a4c}]</property>
                        </object>
                    </property>
                    <property name="expression" valueType="table">
                        <object type="DataModel:fieldReference" version="1.0">
                            <property name="value" valueType="url">DataModel["F_414_FACTORING__PGD_TR"{25e8ebb7-3cad-4363-b464-d40e1e9f2a4c}].hierarchy["TR_PARAMETROS_F414"{ae9d3ed1-dbe9-48a0-9806-aa645d8b124f}].dataSource.layout["VARIABLE"{c00e0aa3-849a-433c-91b0-c9a065200ead}]</property>
                        </object>
                    </property>
                </object>
            </property>
        </object>
        <object type="Aggregation:mapping" version="2.0">
            <property name="field" valueType="object">
                <object type="Aggregation:localDetailReference" version="1.0">
                    <property name="value" valueType="url">Aggregation[this].details["VALOR_MIN"{3443d53f-9c1a-4ecf-96ea-76130f793e1a}]</property>
                </object>
            </property>
            <property name="fieldMapping" valueType="table">
                <object type="FieldMapping" version="2.0">
                    <property name="model" valueType="object">
                        <object type="DataModel:reference" version="1.0">
                            <property name="value" valueType="url">DataModel["F_414_FACTORING__PGD_TR"{25e8ebb7-3cad-4363-b464-d40e1e9f2a4c}]</property>
                        </object>
                    </property>
                    <property name="expression" valueType="table">
                        <object type="DataModel:fieldReference" version="1.0">
                            <property name="value" valueType="url">DataModel["F_414_FACTORING__PGD_TR"{25e8ebb7-3cad-4363-b464-d40e1e9f2a4c}].hierarchy["TR_PARAMETROS_F414"{ae9d3ed1-dbe9-48a0-9806-aa645d8b124f}].dataSource.layout["VALOR_MIN"{5da8c723-d80c-4d4f-a43f-f03d95c5a276}]</property>
                        </object>
                    </property>
                </object>
            </property>
        </object>
        <object type="Aggregation:mapping" version="2.0">
            <property name="field" valueType="object">
                <object type="Aggregation:localDetailReference" version="1.0">
                    <property name="value" valueType="url">Aggregation[this].details["VALOR_MAX"{b9e4dedb-fad7-40f8-84b8-c7bc984f8823}]</property>
                </object>
            </property>
            <property name="fieldMapping" valueType="table">
                <object type="FieldMapping" version="2.0">
                    <property name="model" valueType="object">
                        <object type="DataModel:reference" version="1.0">
                            <property name="value" valueType="url">DataModel["F_414_FACTORING__PGD_TR"{25e8ebb7-3cad-4363-b464-d40e1e9f2a4c}]</property>
                        </object>
                    </property>
                    <property name="expression" valueType="table">
                        <object type="DataModel:fieldReference" version="1.0">
                            <property name="value" valueType="url">DataModel["F_414_FACTORING__PGD_TR"{25e8ebb7-3cad-4363-b464-d40e1e9f2a4c}].hierarchy["TR_PARAMETROS_F414"{ae9d3ed1-dbe9-48a0-9806-aa645d8b124f}].dataSource.layout["VALOR_MAX"{eff3d911-a3b9-4dba-941a-095ec425c99f}]</property>
                        </object>
                    </property>
                </object>
            </property>
        </object>
        <object type="Aggregation:mapping" version="2.0">
            <property name="field" valueType="object">
                <object type="Aggregation:localDetailReference" version="1.0">
                    <property name="value" valueType="url">Aggregation[this].details["DOCBCO"{7508d293-4003-4eb4-a3aa-332c40f8256f}]</property>
                </object>
            </property>
            <property name="fieldMapping" valueType="table">
                <object type="FieldMapping" version="2.0">
                    <property name="model" valueType="object">
                        <object type="DataModel:reference" version="1.0">
                            <property name="value" valueType="url">DataModel["F_414_FACTORING__PGD_TR"{25e8ebb7-3cad-4363-b464-d40e1e9f2a4c}]</property>
                        </object>
                    </property>
                    <property name="expression" valueType="table">
                        <object type="DataModel:fieldReference" version="1.0">
                            <property name="value" valueType="url">DataModel["F_414_FACTORING__PGD_TR"{25e8ebb7-3cad-4363-b464-d40e1e9f2a4c}].hierarchy["root"{f5507474-dc3c-484a-9fbd-c2278563d213}].dataSource.layout["DOCBCO"{7956a287-c1af-4917-977c-fa653b19113c}]</property>
                        </object>
                    </property>
                </object>
            </property>
        </object>
        <object type="Aggregation:mapping" version="2.0">
            <property name="field" valueType="object">
                <object type="Aggregation:localDetailReference" version="1.0">
                    <property name="value" valueType="url">Aggregation[this].details["SEGMENTO_PAG"{9497e644-47b2-41bf-adc1-942d2876203c}]</property>
                </object>
            </property>
            <property name="fieldMapping" valueType="table">
                <object type="FieldMapping" version="2.0">
                    <property name="model" valueType="object">
                        <object type="DataModel:reference" version="1.0">
                            <property name="value" valueType="url">DataModel["F_414_FACTORING__PGD_TR"{25e8ebb7-3cad-4363-b464-d40e1e9f2a4c}]</property>
                        </object>
                    </property>
                    <property name="expression" valueType="table">
                        <object type="DataModel:fieldReference" version="1.0">
                            <property name="value" valueType="url">DataModel["F_414_FACTORING__PGD_TR"{25e8ebb7-3cad-4363-b464-d40e1e9f2a4c}].hierarchy["root"{f5507474-dc3c-484a-9fbd-c2278563d213}].dataSource.layout["SEGMENTO_PAG"{f2444972-344c-4d6d-9fee-d01bf1967507}]</property>
                        </object>
                    </property>
                </object>
            </property>
        </object>
        <object type="Aggregation:mapping" version="2.0">
            <property name="field" valueType="object">
                <object type="Aggregation:localDetailReference" version="1.0">
                    <property name="value" valueType="url">Aggregation[this].details["FECHAVENCE"{cfc594fe-e0bc-45e3-99aa-9bcde4de2660}]</property>
                </object>
            </property>
            <property name="fieldMapping" valueType="table">
                <object type="FieldMapping" version="2.0">
                    <property name="model" valueType="object">
                        <object type="DataModel:reference" version="1.0">
                            <property name="value" valueType="url">DataModel["F_414_FACTORING__PGD_TR"{25e8ebb7-3cad-4363-b464-d40e1e9f2a4c}]</property>
                        </object>
                    </property>
                    <property name="expression" valueType="table">
                        <object type="DataModel:fieldReference" version="1.0">
                            <property name="value" valueType="url">DataModel["F_414_FACTORING__PGD_TR"{25e8ebb7-3cad-4363-b464-d40e1e9f2a4c}].hierarchy["root"{f5507474-dc3c-484a-9fbd-c2278563d213}].dataSource.layout["FECHAVENCE"{afaba42a-05db-4e8e-9192-92767d4accd9}]</property>
                        </object>
                    </property>
                </object>
            </property>
        </object>
        <object type="Aggregation:mapping" version="2.0">
            <property name="field" valueType="object">
                <object type="Aggregation:localCalcFieldReference" version="1.0">
                    <property name="value" valueType="url">Aggregation[this].calcFields["GVALOR"{ea8adf66-bb25-4574-bf2b-71e3dd435465}]</property>
                </object>
            </property>
            <property name="fieldMapping" valueType="table">
                <object type="FieldMapping" version="2.0">
                    <property name="model" valueType="object">
                        <object type="DataModel:reference" version="1.0">
                            <property name="value" valueType="url">DataModel["F_414_FACTORING__PGD_TR"{25e8ebb7-3cad-4363-b464-d40e1e9f2a4c}]</property>
                        </object>
                    </property>
                    <property name="expression" valueType="table">
                        <object type="DataModel:fieldReference" version="1.0">
                            <property name="value" valueType="url">DataModel["F_414_FACTORING__PGD_TR"{25e8ebb7-3cad-4363-b464-d40e1e9f2a4c}].hierarchy["root"{f5507474-dc3c-484a-9fbd-c2278563d213}].dataSource.layout["GVALOR"{17c0ba5b-3a01-48ed-b303-17819a7de7f1}]</property>
                        </object>
                    </property>
                </object>
            </property>
        </object>
        <object type="Aggregation:mapping" version="2.0">
            <property name="field" valueType="object">
                <object type="Aggregation:localCalcFieldReference" version="1.0">
                    <property name="value" valueType="url">Aggregation[this].calcFields["TASAINTREM"{babfb5e9-b5b6-4874-851e-e5a8636b1e76}]</property>
                </object>
            </property>
            <property name="fieldMapping" valueType="table">
                <object type="FieldMapping" version="2.0">
                    <property name="model" valueType="object">
                        <object type="DataModel:reference" version="1.0">
                            <property name="value" valueType="url">DataModel["F_414_FACTORING__PGD_TR"{25e8ebb7-3cad-4363-b464-d40e1e9f2a4c}]</property>
                        </object>
                    </property>
                    <property name="expression" valueType="table">
                        <object type="DataModel:fieldReference" version="1.0">
                            <property name="value" valueType="url">DataModel["F_414_FACTORING__PGD_TR"{25e8ebb7-3cad-4363-b464-d40e1e9f2a4c}].hierarchy["root"{f5507474-dc3c-484a-9fbd-c2278563d213}].dataSource.layout["TASAINTREM"{c20d6745-fcbc-46f9-bc39-abe1b1beba51}]</property>
                        </object>
                    </property>
                </object>
            </property>
        </object>
        <object type="Aggregation:mapping" version="2.0">
            <property name="field" valueType="object">
                <object type="Aggregation:localCalcFieldReference" version="1.0">
                    <property name="value" valueType="url">Aggregation[this].calcFields["VALPAGCAPI"{73b01307-0934-40ed-8e8f-2abba35609f9}]</property>
                </object>
            </property>
            <property name="fieldMapping" valueType="table">
                <object type="FieldMapping" version="2.0">
                    <property name="model" valueType="object">
                        <object type="DataModel:reference" version="1.0">
                            <property name="value" valueType="url">DataModel["F_414_FACTORING__PGD_TR"{25e8ebb7-3cad-4363-b464-d40e1e9f2a4c}]</property>
                        </object>
                    </property>
                    <property name="expression" valueType="table">
                        <object type="DataModel:fieldReference" version="1.0">
                            <property name="value" valueType="url">DataModel["F_414_FACTORING__PGD_TR"{25e8ebb7-3cad-4363-b464-d40e1e9f2a4c}].hierarchy["root"{f5507474-dc3c-484a-9fbd-c2278563d213}].dataSource.layout["VALPAGCAPI"{8816ba92-d133-4f70-b418-de8118501911}]</property>
                        </object>
                    </property>
                </object>
            </property>
        </object>
        <object type="Aggregation:mapping" version="2.0">
            <property name="field" valueType="object">
                <object type="Aggregation:localCalcFieldReference" version="1.0">
                    <property name="value" valueType="url">Aggregation[this].calcFields["GVALORN"{629e40c9-e5d7-4fbd-839b-4cd20067e386}]</property>
                </object>
            </property>
            <property name="fieldMapping" valueType="table">
                <object type="FieldMapping" version="2.0">
                    <property name="model" valueType="object">
                        <object type="DataModel:reference" version="1.0">
                            <property name="value" valueType="url">DataModel["F_414_FACTORING__PGD_TR"{25e8ebb7-3cad-4363-b464-d40e1e9f2a4c}]</property>
                        </object>
                    </property>
                    <property name="expression" valueType="table">
                        <object type="DataModel:fieldReference" version="1.0">
                            <property name="value" valueType="url">DataModel["F_414_FACTORING__PGD_TR"{25e8ebb7-3cad-4363-b464-d40e1e9f2a4c}].hierarchy["root"{f5507474-dc3c-484a-9fbd-c2278563d213}].dataSource.layout["GVALORN"{86261b2b-cc4b-49f2-ba43-5f8dde20e601}]</property>
                        </object>
                    </property>
                </object>
            </property>
        </object>
        <object type="Aggregation:mapping" version="2.0">
            <property name="field" valueType="object">
                <object type="Aggregation:localCalcFieldReference" version="1.0">
                    <property name="value" valueType="url">Aggregation[this].calcFields["VLRAMORTI"{3a5d3145-fd16-49ad-b049-d2fc45e8d3f1}]</property>
                </object>
            </property>
            <property name="fieldMapping" valueType="table">
                <object type="FieldMapping" version="2.0">
                    <property name="model" valueType="object">
                        <object type="DataModel:reference" version="1.0">
                            <property name="value" valueType="url">DataModel["F_414_FACTORING__PGD_TR"{25e8ebb7-3cad-4363-b464-d40e1e9f2a4c}]</property>
                        </object>
                    </property>
                    <property name="expression" valueType="table">
                        <object type="DataModel:fieldReference" version="1.0">
                            <property name="value" valueType="url">DataModel["F_414_FACTORING__PGD_TR"{25e8ebb7-3cad-4363-b464-d40e1e9f2a4c}].hierarchy["root"{f5507474-dc3c-484a-9fbd-c2278563d213}].dataSource.layout["VLRAMORTI"{ea7d5c6b-60b4-4ccf-95ec-b7c72b927e76}]</property>
                        </object>
                    </property>
                </object>
            </property>
        </object>
        <object type="Aggregation:mapping" version="2.0">
            <property name="field" valueType="object">
                <object type="Aggregation:localCalcFieldReference" version="1.0">
                    <property name="value" valueType="url">Aggregation[this].calcFields["PLAZO_DIA_PGADOR"{b4c20227-0784-4065-ad5c-7d919dd1c483}]</property>
                </object>
            </property>
            <property name="fieldMapping" valueType="table">
                <object type="FieldMapping" version="2.0">
                    <property name="model" valueType="object">
                        <object type="DataModel:reference" version="1.0">
                            <property name="value" valueType="url">DataModel["F_414_FACTORING__PGD_TR"{25e8ebb7-3cad-4363-b464-d40e1e9f2a4c}]</property>
                        </object>
                    </property>
                    <property name="expression" valueType="table">
                        <object type="DataModel:fieldReference" version="1.0">
                            <property name="value" valueType="url">DataModel["F_414_FACTORING__PGD_TR"{25e8ebb7-3cad-4363-b464-d40e1e9f2a4c}].hierarchy["root"{f5507474-dc3c-484a-9fbd-c2278563d213}].dataSource.layout["PLAZO_DIA_PGADOR"{8da17683-7797-43fa-a922-c469d7efe5a1}]</property>
                        </object>
                    </property>
                </object>
            </property>
        </object>
        <object type="Aggregation:mapping" version="2.0">
            <property name="field" valueType="object">
                <object type="Aggregation:localCalcFieldReference" version="1.0">
                    <property name="value" valueType="url">Aggregation[this].calcFields["TASA_EFECTIVA_CON_PAG"{7f48362b-ed64-4518-94c5-2f21ba67051e}]</property>
                </object>
            </property>
            <property name="fieldMapping" valueType="table">
                <object type="FieldMapping" version="2.0">
                    <property name="model" valueType="object">
                        <object type="DataModel:reference" version="1.0">
                            <property name="value" valueType="url">DataModel["F_414_FACTORING__PGD_TR"{25e8ebb7-3cad-4363-b464-d40e1e9f2a4c}]</property>
                        </object>
                    </property>
                    <property name="expression" valueType="table">
                        <object type="DataModel:fieldReference" version="1.0">
                            <property name="value" valueType="url">DataModel["F_414_FACTORING__PGD_TR"{25e8ebb7-3cad-4363-b464-d40e1e9f2a4c}].hierarchy["root"{f5507474-dc3c-484a-9fbd-c2278563d213}].dataSource.layout["TASA_EFECTIVA_CON_PAG"{6648070a-7e28-47b2-a519-24f6268e3c92}]</property>
                        </object>
                    </property>
                </object>
            </property>
        </object>
        <object type="Aggregation:mapping" version="2.0">
            <property name="field" valueType="object">
                <object type="Aggregation:localCalcFieldReference" version="1.0">
                    <property name="value" valueType="url">Aggregation[this].calcFields["TASA_EFECTIVA_SIN_PAG"{9830b6f1-afe2-423f-bde4-d00e0c61b8aa}]</property>
                </object>
            </property>
            <property name="fieldMapping" valueType="table">
                <object type="FieldMapping" version="2.0">
                    <property name="model" valueType="object">
                        <object type="DataModel:reference" version="1.0">
                            <property name="value" valueType="url">DataModel["F_414_FACTORING__PGD_TR"{25e8ebb7-3cad-4363-b464-d40e1e9f2a4c}]</property>
                        </object>
                    </property>
                    <property name="expression" valueType="table">
                        <object type="DataModel:fieldReference" version="1.0">
                            <property name="value" valueType="url">DataModel["F_414_FACTORING__PGD_TR"{25e8ebb7-3cad-4363-b464-d40e1e9f2a4c}].hierarchy["root"{f5507474-dc3c-484a-9fbd-c2278563d213}].dataSource.layout["TASA_EFECTIVA_SIN_PAG"{9e53fbb8-be85-4e46-8701-d5891cf072ef}]</property>
                        </object>
                    </property>
                </object>
            </property>
        </object>
    </property>
    <property name="storageType" value="CONTINUOUS_PARTITION" valueType="string"/>
    <property name="postTableCreationStatements" valueType="table"/>
    <property name="postAdjustmentTableCreationStatements" valueType="table"/>
    <property name="detailsAsKeys" value="false" valueType="boolean"/>
    <property name="dbSourceForResults" valueType="url">DBSource["SHLEGALP"{989aedc8-de34-46f9-bc09-198909e09676}]</property>
    <property name="condition" valueType="object">
        <object type="DataModelCondition" version="1.0">
            <property name="conditionTree" valueType="tree">
                <objectNode type="Condition:compositeCondition" version="1.0">
                    <property name="isNegated" value="false" valueType="boolean"/>
                    <property name="groupingOperator" value="AND" valueType="string"/>
                    <children>
                        <objectNode type="DataModelCondition:shorthand" version="1.0">
                            <property name="shorthand" valueType="url">Shorthand["F_414_PRODUCTOS"{47dd6bfc-99a7-49c6-b9e8-9f2fb94e9f7e}]</property>
                            <property name="operation" value="=" valueType="string"/>
                        </objectNode>
                    </children>
                </objectNode>
            </property>
        </object>
    </property>
    <property name="doNotAggregate" value="false" valueType="boolean"/>
    <property name="fourEyesCheck" value="false" valueType="boolean"/>
    <property name="trackDrilldownInformation" value="true" valueType="boolean"/>
    <property name="trackAllInstancesMode" value="NONE" valueType="string"/>
    <property name="computeStatistics" value="FOR_ALL_COLUMNS" valueType="string"/>
    <property name="makeStreamColumnsKey" value="true" valueType="boolean"/>
    <property name="instanceRebuildRestriction" value="AlterFullRebuild" valueType="string"/>
    <property name="allowExternalDataPermissions" value="true" valueType="boolean"/>
    <property name="docData" valueType="object">
        <object type="DocData" version="1.0">
            <property name="comment" value="Creación:&#x9;05-apr-2022&#xa;Analista:&#x9;caalmosq&#xa;Objetivo:&#x9;se crea agg con el cruce de infromacion de factoring pagador con la tabla parametrica" valueType="string"/>
        </object>
    </property>
</object>